{"growth": "linear", "n_changepoints": 15, "specified_changepoints": false, "changepoint_range": 0.8, "yearly_seasonality": "auto", "weekly_seasonality": 52, "daily_seasonality": "auto", "seasonality_mode": "additive", "seasonality_prior_scale": 10.0, "changepoint_prior_scale": 0.05, "holidays_prior_scale": 10.0, "mcmc_samples": 0, "interval_width": 0.8, "uncertainty_samples": 1000, "y_scale": 5.0, "y_min": 0.0, "scaling": "absmax", "logistic_floor": false, "country_holidays": null, "component_modes": {"additive": ["yearly", "weekly", "campaign", "discount_for_event", "additive_terms", "extra_regressors_additive", "holidays"], "multiplicative": ["multiplicative_terms", "extra_regressors_multiplicative"]}, "holidays_mode": "additive", "changepoints": "{\"name\":\"ds\",\"index\":[1,2,3,4,5,6,7,8,9,10,11,12,13,14,15],\"data\":[\"2018-07-09T00:00:00.000\",\"2018-07-16T00:00:00.000\",\"2018-07-23T00:00:00.000\",\"2018-07-30T00:00:00.000\",\"2018-08-06T00:00:00.000\",\"2018-08-13T00:00:00.000\",\"2018-08-20T00:00:00.000\",\"2019-02-04T00:00:00.000\",\"2019-07-01T00:00:00.000\",\"2019-07-15T00:00:00.000\",\"2019-07-22T00:00:00.000\",\"2019-07-29T00:00:00.000\",\"2019-08-05T00:00:00.000\",\"2019-08-12T00:00:00.000\",\"2019-09-02T00:00:00.000\"]}", "history_dates": "{\"name\":\"ds\",\"index\":[0,1,2,3,4,5,6,7,8,9,10,11,12,13,14,15,16,17,18,19],\"data\":[\"2018-01-22T00:00:00.000\",\"2018-07-09T00:00:00.000\",\"2018-07-16T00:00:00.000\",\"2018-07-23T00:00:00.000\",\"2018-07-30T00:00:00.000\",\"2018-08-06T00:00:00.000\",\"2018-08-13T00:00:00.000\",\"2018-08-20T00:00:00.000\",\"2019-02-04T00:00:00.000\",\"2019-07-01T00:00:00.000\",\"2019-07-15T00:00:00.000\",\"2019-07-22T00:00:00.000\",\"2019-07-29T00:00:00.000\",\"2019-08-05T00:00:00.000\",\"2019-08-12T00:00:00.000\",\"2019-09-02T00:00:00.000\",\"2019-12-09T00:00:00.000\",\"2020-01-06T00:00:00.000\",\"2020-01-13T00:00:00.000\",\"2020-06-29T00:00:00.000\"]}", "train_holiday_names": null, "start": 1516579200.0, "t_scale": 76809600.0, "holidays": null, "history": "{\"schema\":{\"fields\":[{\"name\":\"ds\",\"type\":\"datetime\"},{\"name\":\"y\",\"type\":\"integer\"},{\"name\":\"campaign\",\"type\":\"number\"},{\"name\":\"discount_for_event\",\"type\":\"number\"},{\"name\":\"floor\",\"type\":\"number\"},{\"name\":\"t\",\"type\":\"number\"},{\"name\":\"y_scaled\",\"type\":\"number\"}],\"pandas_version\":\"1.4.0\"},\"data\":[{\"ds\":\"2018-01-22T00:00:00.000\",\"y\":1,\"campaign\":0.0,\"discount_for_event\":0.0,\"floor\":0.0,\"t\":0.0,\"y_scaled\":0.2},{\"ds\":\"2018-07-09T00:00:00.000\",\"y\":2,\"campaign\":1.0,\"discount_for_event\":0.0,\"floor\":0.0,\"t\":0.188976378,\"y_scaled\":0.4},{\"ds\":\"2018-07-16T00:00:00.000\",\"y\":2,\"campaign\":0.0,\"discount_for_event\":0.0,\"floor\":0.0,\"t\":0.1968503937,\"y_scaled\":0.4},{\"ds\":\"2018-07-23T00:00:00.000\",\"y\":1,\"campaign\":0.0,\"discount_for_event\":0.0,\"floor\":0.0,\"t\":0.2047244094,\"y_scaled\":0.2},{\"ds\":\"2018-07-30T00:00:00.000\",\"y\":1,\"campaign\":1.0,\"discount_for_event\":0.0,\"floor\":0.0,\"t\":0.2125984252,\"y_scaled\":0.2},{\"ds\":\"2018-08-06T00:00:00.000\",\"y\":3,\"campaign\":1.0,\"discount_for_event\":0.0,\"floor\":0.0,\"t\":0.2204724409,\"y_scaled\":0.6},{\"ds\":\"2018-08-13T00:00:00.000\",\"y\":5,\"campaign\":1.0,\"discount_for_event\":0.0,\"floor\":0.0,\"t\":0.2283464567,\"y_scaled\":1.0},{\"ds\":\"2018-08-20T00:00:00.000\",\"y\":1,\"campaign\":1.0,\"discount_for_event\":0.0,\"floor\":0.0,\"t\":0.2362204724,\"y_scaled\":0.2},{\"ds\":\"2019-02-04T00:00:00.000\",\"y\":1,\"campaign\":1.0,\"discount_for_event\":0.0,\"floor\":0.0,\"t\":0.4251968504,\"y_scaled\":0.2},{\"ds\":\"2019-07-01T00:00:00.000\",\"y\":1,\"campaign\":1.0,\"discount_for_event\":0.0,\"floor\":0.0,\"t\":0.5905511811,\"y_scaled\":0.2},{\"ds\":\"2019-07-15T00:00:00.000\",\"y\":1,\"campaign\":1.0,\"discount_for_event\":0.0,\"floor\":0.0,\"t\":0.6062992126,\"y_scaled\":0.2},{\"ds\":\"2019-07-22T00:00:00.000\",\"y\":1,\"campaign\":1.0,\"discount_for_event\":0.0,\"floor\":0.0,\"t\":0.6141732283,\"y_scaled\":0.2},{\"ds\":\"2019-07-29T00:00:00.000\",\"y\":5,\"campaign\":1.0,\"discount_for_event\":0.0,\"floor\":0.0,\"t\":0.6220472441,\"y_scaled\":1.0},{\"ds\":\"2019-08-05T00:00:00.000\",\"y\":4,\"campaign\":0.0,\"discount_for_event\":0.0,\"floor\":0.0,\"t\":0.6299212598,\"y_scaled\":0.8},{\"ds\":\"2019-08-12T00:00:00.000\",\"y\":2,\"campaign\":0.0,\"discount_for_event\":0.0,\"floor\":0.0,\"t\":0.6377952756,\"y_scaled\":0.4},{\"ds\":\"2019-09-02T00:00:00.000\",\"y\":1,\"campaign\":1.0,\"discount_for_event\":0.0,\"floor\":0.0,\"t\":0.6614173228,\"y_scaled\":0.2},{\"ds\":\"2019-12-09T00:00:00.000\",\"y\":1,\"campaign\":0.0,\"discount_for_event\":0.0,\"floor\":0.0,\"t\":0.7716535433,\"y_scaled\":0.2},{\"ds\":\"2020-01-06T00:00:00.000\",\"y\":1,\"campaign\":0.0,\"discount_for_event\":0.0,\"floor\":0.0,\"t\":0.8031496063,\"y_scaled\":0.2},{\"ds\":\"2020-01-13T00:00:00.000\",\"y\":2,\"campaign\":0.0,\"discount_for_event\":0.0,\"floor\":0.0,\"t\":0.811023622,\"y_scaled\":0.4},{\"ds\":\"2020-06-29T00:00:00.000\",\"y\":1,\"campaign\":0.0,\"discount_for_event\":0.0,\"floor\":0.0,\"t\":1.0,\"y_scaled\":0.2}]}", "train_component_cols": "{\"schema\":{\"fields\":[{\"name\":\"additive_terms\",\"type\":\"integer\"},{\"name\":\"campaign\",\"type\":\"integer\"},{\"name\":\"discount_for_event\",\"type\":\"integer\"},{\"name\":\"extra_regressors_additive\",\"type\":\"integer\"},{\"name\":\"weekly\",\"type\":\"integer\"},{\"name\":\"yearly\",\"type\":\"integer\"},{\"name\":\"multiplicative_terms\",\"type\":\"integer\"}],\"pandas_version\":\"1.4.0\"},\"data\":[{\"additive_terms\":1,\"campaign\":0,\"discount_for_event\":0,\"extra_regressors_additive\":0,\"weekly\":0,\"yearly\":1,\"multiplicative_terms\":0},{\"additive_terms\":1,\"campaign\":0,\"discount_for_event\":0,\"extra_regressors_additive\":0,\"weekly\":0,\"yearly\":1,\"multiplicative_terms\":0},{\"additive_terms\":1,\"campaign\":0,\"discount_for_event\":0,\"extra_regressors_additive\":0,\"weekly\":0,\"yearly\":1,\"multiplicative_terms\":0},{\"additive_terms\":1,\"campaign\":0,\"discount_for_event\":0,\"extra_regressors_additive\":0,\"weekly\":0,\"yearly\":1,\"multiplicative_terms\":0},{\"additive_terms\":1,\"campaign\":0,\"discount_for_event\":0,\"extra_regressors_additive\":0,\"weekly\":0,\"yearly\":1,\"multiplicative_terms\":0},{\"additive_terms\":1,\"campaign\":0,\"discount_for_event\":0,\"extra_regressors_additive\":0,\"weekly\":0,\"yearly\":1,\"multiplicative_terms\":0},{\"additive_terms\":1,\"campaign\":0,\"discount_for_event\":0,\"extra_regressors_additive\":0,\"weekly\":0,\"yearly\":1,\"multiplicative_terms\":0},{\"additive_terms\":1,\"campaign\":0,\"discount_for_event\":0,\"extra_regressors_additive\":0,\"weekly\":0,\"yearly\":1,\"multiplicative_terms\":0},{\"additive_terms\":1,\"campaign\":0,\"discount_for_event\":0,\"extra_regressors_additive\":0,\"weekly\":0,\"yearly\":1,\"multiplicative_terms\":0},{\"additive_terms\":1,\"campaign\":0,\"discount_for_event\":0,\"extra_regressors_additive\":0,\"weekly\":0,\"yearly\":1,\"multiplicative_terms\":0},{\"additive_terms\":1,\"campaign\":0,\"discount_for_event\":0,\"extra_regressors_additive\":0,\"weekly\":0,\"yearly\":1,\"multiplicative_terms\":0},{\"additive_terms\":1,\"campaign\":0,\"discount_for_event\":0,\"extra_regressors_additive\":0,\"weekly\":0,\"yearly\":1,\"multiplicative_terms\":0},{\"additive_terms\":1,\"campaign\":0,\"discount_for_event\":0,\"extra_regressors_additive\":0,\"weekly\":0,\"yearly\":1,\"multiplicative_terms\":0},{\"additive_terms\":1,\"campaign\":0,\"discount_for_event\":0,\"extra_regressors_additive\":0,\"weekly\":0,\"yearly\":1,\"multiplicative_terms\":0},{\"additive_terms\":1,\"campaign\":0,\"discount_for_event\":0,\"extra_regressors_additive\":0,\"weekly\":0,\"yearly\":1,\"multiplicative_terms\":0},{\"additive_terms\":1,\"campaign\":0,\"discount_for_event\":0,\"extra_regressors_additive\":0,\"weekly\":0,\"yearly\":1,\"multiplicative_terms\":0},{\"additive_terms\":1,\"campaign\":0,\"discount_for_event\":0,\"extra_regressors_additive\":0,\"weekly\":0,\"yearly\":1,\"multiplicative_terms\":0},{\"additive_terms\":1,\"campaign\":0,\"discount_for_event\":0,\"extra_regressors_additive\":0,\"weekly\":0,\"yearly\":1,\"multiplicative_terms\":0},{\"additive_terms\":1,\"campaign\":0,\"discount_for_event\":0,\"extra_regressors_additive\":0,\"weekly\":0,\"yearly\":1,\"multiplicative_terms\":0},{\"additive_terms\":1,\"campaign\":0,\"discount_for_event\":0,\"extra_regressors_additive\":0,\"weekly\":0,\"yearly\":1,\"multiplicative_terms\":0},{\"additive_terms\":1,\"campaign\":0,\"discount_for_event\":0,\"extra_regressors_additive\":0,\"weekly\":1,\"yearly\":0,\"multiplicative_terms\":0},{\"additive_terms\":1,\"campaign\":0,\"discount_for_event\":0,\"extra_regressors_additive\":0,\"weekly\":1,\"yearly\":0,\"multiplicative_terms\":0},{\"additive_terms\":1,\"campaign\":0,\"discount_for_event\":0,\"extra_regressors_additive\":0,\"weekly\":1,\"yearly\":0,\"multiplicative_terms\":0},{\"additive_terms\":1,\"campaign\":0,\"discount_for_event\":0,\"extra_regressors_additive\":0,\"weekly\":1,\"yearly\":0,\"multiplicative_terms\":0},{\"additive_terms\":1,\"campaign\":0,\"discount_for_event\":0,\"extra_regressors_additive\":0,\"weekly\":1,\"yearly\":0,\"multiplicative_terms\":0},{\"additive_terms\":1,\"campaign\":0,\"discount_for_event\":0,\"extra_regressors_additive\":0,\"weekly\":1,\"yearly\":0,\"multiplicative_terms\":0},{\"additive_terms\":1,\"campaign\":0,\"discount_for_event\":0,\"extra_regressors_additive\":0,\"weekly\":1,\"yearly\":0,\"multiplicative_terms\":0},{\"additive_terms\":1,\"campaign\":0,\"discount_for_event\":0,\"extra_regressors_additive\":0,\"weekly\":1,\"yearly\":0,\"multiplicative_terms\":0},{\"additive_terms\":1,\"campaign\":0,\"discount_for_event\":0,\"extra_regressors_additive\":0,\"weekly\":1,\"yearly\":0,\"multiplicative_terms\":0},{\"additive_terms\":1,\"campaign\":0,\"discount_for_event\":0,\"extra_regressors_additive\":0,\"weekly\":1,\"yearly\":0,\"multiplicative_terms\":0},{\"additive_terms\":1,\"campaign\":0,\"discount_for_event\":0,\"extra_regressors_additive\":0,\"weekly\":1,\"yearly\":0,\"multiplicative_terms\":0},{\"additive_terms\":1,\"campaign\":0,\"discount_for_event\":0,\"extra_regressors_additive\":0,\"weekly\":1,\"yearly\":0,\"multiplicative_terms\":0},{\"additive_terms\":1,\"campaign\":0,\"discount_for_event\":0,\"extra_regressors_additive\":0,\"weekly\":1,\"yearly\":0,\"multiplicative_terms\":0},{\"additive_terms\":1,\"campaign\":0,\"discount_for_event\":0,\"extra_regressors_additive\":0,\"weekly\":1,\"yearly\":0,\"multiplicative_terms\":0},{\"additive_terms\":1,\"campaign\":0,\"discount_for_event\":0,\"extra_regressors_additive\":0,\"weekly\":1,\"yearly\":0,\"multiplicative_terms\":0},{\"additive_terms\":1,\"campaign\":0,\"discount_for_event\":0,\"extra_regressors_additive\":0,\"weekly\":1,\"yearly\":0,\"multiplicative_terms\":0},{\"additive_terms\":1,\"campaign\":0,\"discount_for_event\":0,\"extra_regressors_additive\":0,\"weekly\":1,\"yearly\":0,\"multiplicative_terms\":0},{\"additive_terms\":1,\"campaign\":0,\"discount_for_event\":0,\"extra_regressors_additive\":0,\"weekly\":1,\"yearly\":0,\"multiplicative_terms\":0},{\"additive_terms\":1,\"campaign\":0,\"discount_for_event\":0,\"extra_regressors_additive\":0,\"weekly\":1,\"yearly\":0,\"multiplicative_terms\":0},{\"additive_terms\":1,\"campaign\":0,\"discount_for_event\":0,\"extra_regressors_additive\":0,\"weekly\":1,\"yearly\":0,\"multiplicative_terms\":0},{\"additive_terms\":1,\"campaign\":0,\"discount_for_event\":0,\"extra_regressors_additive\":0,\"weekly\":1,\"yearly\":0,\"multiplicative_terms\":0},{\"additive_terms\":1,\"campaign\":0,\"discount_for_event\":0,\"extra_regressors_additive\":0,\"weekly\":1,\"yearly\":0,\"multiplicative_terms\":0},{\"additive_terms\":1,\"campaign\":0,\"discount_for_event\":0,\"extra_regressors_additive\":0,\"weekly\":1,\"yearly\":0,\"multiplicative_terms\":0},{\"additive_terms\":1,\"campaign\":0,\"discount_for_event\":0,\"extra_regressors_additive\":0,\"weekly\":1,\"yearly\":0,\"multiplicative_terms\":0},{\"additive_terms\":1,\"campaign\":0,\"discount_for_event\":0,\"extra_regressors_additive\":0,\"weekly\":1,\"yearly\":0,\"multiplicative_terms\":0},{\"additive_terms\":1,\"campaign\":0,\"discount_for_event\":0,\"extra_regressors_additive\":0,\"weekly\":1,\"yearly\":0,\"multiplicative_terms\":0},{\"additive_terms\":1,\"campaign\":0,\"discount_for_event\":0,\"extra_regressors_additive\":0,\"weekly\":1,\"yearly\":0,\"multiplicative_terms\":0},{\"additive_terms\":1,\"campaign\":0,\"discount_for_event\":0,\"extra_regressors_additive\":0,\"weekly\":1,\"yearly\":0,\"multiplicative_terms\":0},{\"additive_terms\":1,\"campaign\":0,\"discount_for_event\":0,\"extra_regressors_additive\":0,\"weekly\":1,\"yearly\":0,\"multiplicative_terms\":0},{\"additive_terms\":1,\"campaign\":0,\"discount_for_event\":0,\"extra_regressors_additive\":0,\"weekly\":1,\"yearly\":0,\"multiplicative_terms\":0},{\"additive_terms\":1,\"campaign\":0,\"discount_for_event\":0,\"extra_regressors_additive\":0,\"weekly\":1,\"yearly\":0,\"multiplicative_terms\":0},{\"additive_terms\":1,\"campaign\":0,\"discount_for_event\":0,\"extra_regressors_additive\":0,\"weekly\":1,\"yearly\":0,\"multiplicative_terms\":0},{\"additive_terms\":1,\"campaign\":0,\"discount_for_event\":0,\"extra_regressors_additive\":0,\"weekly\":1,\"yearly\":0,\"multiplicative_terms\":0},{\"additive_terms\":1,\"campaign\":0,\"discount_for_event\":0,\"extra_regressors_additive\":0,\"weekly\":1,\"yearly\":0,\"multiplicative_terms\":0},{\"additive_terms\":1,\"campaign\":0,\"discount_for_event\":0,\"extra_regressors_additive\":0,\"weekly\":1,\"yearly\":0,\"multiplicative_terms\":0},{\"additive_terms\":1,\"campaign\":0,\"discount_for_event\":0,\"extra_regressors_additive\":0,\"weekly\":1,\"yearly\":0,\"multiplicative_terms\":0},{\"additive_terms\":1,\"campaign\":0,\"discount_for_event\":0,\"extra_regressors_additive\":0,\"weekly\":1,\"yearly\":0,\"multiplicative_terms\":0},{\"additive_terms\":1,\"campaign\":0,\"discount_for_event\":0,\"extra_regressors_additive\":0,\"weekly\":1,\"yearly\":0,\"multiplicative_terms\":0},{\"additive_terms\":1,\"campaign\":0,\"discount_for_event\":0,\"extra_regressors_additive\":0,\"weekly\":1,\"yearly\":0,\"multiplicative_terms\":0},{\"additive_terms\":1,\"campaign\":0,\"discount_for_event\":0,\"extra_regressors_additive\":0,\"weekly\":1,\"yearly\":0,\"multiplicative_terms\":0},{\"additive_terms\":1,\"campaign\":0,\"discount_for_event\":0,\"extra_regressors_additive\":0,\"weekly\":1,\"yearly\":0,\"multiplicative_terms\":0},{\"additive_terms\":1,\"campaign\":0,\"discount_for_event\":0,\"extra_regressors_additive\":0,\"weekly\":1,\"yearly\":0,\"multiplicative_terms\":0},{\"additive_terms\":1,\"campaign\":0,\"discount_for_event\":0,\"extra_regressors_additive\":0,\"weekly\":1,\"yearly\":0,\"multiplicative_terms\":0},{\"additive_terms\":1,\"campaign\":0,\"discount_for_event\":0,\"extra_regressors_additive\":0,\"weekly\":1,\"yearly\":0,\"multiplicative_terms\":0},{\"additive_terms\":1,\"campaign\":0,\"discount_for_event\":0,\"extra_regressors_additive\":0,\"weekly\":1,\"yearly\":0,\"multiplicative_terms\":0},{\"additive_terms\":1,\"campaign\":0,\"discount_for_event\":0,\"extra_regressors_additive\":0,\"weekly\":1,\"yearly\":0,\"multiplicative_terms\":0},{\"additive_terms\":1,\"campaign\":0,\"discount_for_event\":0,\"extra_regressors_additive\":0,\"weekly\":1,\"yearly\":0,\"multiplicative_terms\":0},{\"additive_terms\":1,\"campaign\":0,\"discount_for_event\":0,\"extra_regressors_additive\":0,\"weekly\":1,\"yearly\":0,\"multiplicative_terms\":0},{\"additive_terms\":1,\"campaign\":0,\"discount_for_event\":0,\"extra_regressors_additive\":0,\"weekly\":1,\"yearly\":0,\"multiplicative_terms\":0},{\"additive_terms\":1,\"campaign\":0,\"discount_for_event\":0,\"extra_regressors_additive\":0,\"weekly\":1,\"yearly\":0,\"multiplicative_terms\":0},{\"additive_terms\":1,\"campaign\":0,\"discount_for_event\":0,\"extra_regressors_additive\":0,\"weekly\":1,\"yearly\":0,\"multiplicative_terms\":0},{\"additive_terms\":1,\"campaign\":0,\"discount_for_event\":0,\"extra_regressors_additive\":0,\"weekly\":1,\"yearly\":0,\"multiplicative_terms\":0},{\"additive_terms\":1,\"campaign\":0,\"discount_for_event\":0,\"extra_regressors_additive\":0,\"weekly\":1,\"yearly\":0,\"multiplicative_terms\":0},{\"additive_terms\":1,\"campaign\":0,\"discount_for_event\":0,\"extra_regressors_additive\":0,\"weekly\":1,\"yearly\":0,\"multiplicative_terms\":0},{\"additive_terms\":1,\"campaign\":0,\"discount_for_event\":0,\"extra_regressors_additive\":0,\"weekly\":1,\"yearly\":0,\"multiplicative_terms\":0},{\"additive_terms\":1,\"campaign\":0,\"discount_for_event\":0,\"extra_regressors_additive\":0,\"weekly\":1,\"yearly\":0,\"multiplicative_terms\":0},{\"additive_terms\":1,\"campaign\":0,\"discount_for_event\":0,\"extra_regressors_additive\":0,\"weekly\":1,\"yearly\":0,\"multiplicative_terms\":0},{\"additive_terms\":1,\"campaign\":0,\"discount_for_event\":0,\"extra_regressors_additive\":0,\"weekly\":1,\"yearly\":0,\"multiplicative_terms\":0},{\"additive_terms\":1,\"campaign\":0,\"discount_for_event\":0,\"extra_regressors_additive\":0,\"weekly\":1,\"yearly\":0,\"multiplicative_terms\":0},{\"additive_terms\":1,\"campaign\":0,\"discount_for_event\":0,\"extra_regressors_additive\":0,\"weekly\":1,\"yearly\":0,\"multiplicative_terms\":0},{\"additive_terms\":1,\"campaign\":0,\"discount_for_event\":0,\"extra_regressors_additive\":0,\"weekly\":1,\"yearly\":0,\"multiplicative_terms\":0},{\"additive_terms\":1,\"campaign\":0,\"discount_for_event\":0,\"extra_regressors_additive\":0,\"weekly\":1,\"yearly\":0,\"multiplicative_terms\":0},{\"additive_terms\":1,\"campaign\":0,\"discount_for_event\":0,\"extra_regressors_additive\":0,\"weekly\":1,\"yearly\":0,\"multiplicative_terms\":0},{\"additive_terms\":1,\"campaign\":0,\"discount_for_event\":0,\"extra_regressors_additive\":0,\"weekly\":1,\"yearly\":0,\"multiplicative_terms\":0},{\"additive_terms\":1,\"campaign\":0,\"discount_for_event\":0,\"extra_regressors_additive\":0,\"weekly\":1,\"yearly\":0,\"multiplicative_terms\":0},{\"additive_terms\":1,\"campaign\":0,\"discount_for_event\":0,\"extra_regressors_additive\":0,\"weekly\":1,\"yearly\":0,\"multiplicative_terms\":0},{\"additive_terms\":1,\"campaign\":0,\"discount_for_event\":0,\"extra_regressors_additive\":0,\"weekly\":1,\"yearly\":0,\"multiplicative_terms\":0},{\"additive_terms\":1,\"campaign\":0,\"discount_for_event\":0,\"extra_regressors_additive\":0,\"weekly\":1,\"yearly\":0,\"multiplicative_terms\":0},{\"additive_terms\":1,\"campaign\":0,\"discount_for_event\":0,\"extra_regressors_additive\":0,\"weekly\":1,\"yearly\":0,\"multiplicative_terms\":0},{\"additive_terms\":1,\"campaign\":0,\"discount_for_event\":0,\"extra_regressors_additive\":0,\"weekly\":1,\"yearly\":0,\"multiplicative_terms\":0},{\"additive_terms\":1,\"campaign\":0,\"discount_for_event\":0,\"extra_regressors_additive\":0,\"weekly\":1,\"yearly\":0,\"multiplicative_terms\":0},{\"additive_terms\":1,\"campaign\":0,\"discount_for_event\":0,\"extra_regressors_additive\":0,\"weekly\":1,\"yearly\":0,\"multiplicative_terms\":0},{\"additive_terms\":1,\"campaign\":0,\"discount_for_event\":0,\"extra_regressors_additive\":0,\"weekly\":1,\"yearly\":0,\"multiplicative_terms\":0},{\"additive_terms\":1,\"campaign\":0,\"discount_for_event\":0,\"extra_regressors_additive\":0,\"weekly\":1,\"yearly\":0,\"multiplicative_terms\":0},{\"additive_terms\":1,\"campaign\":0,\"discount_for_event\":0,\"extra_regressors_additive\":0,\"weekly\":1,\"yearly\":0,\"multiplicative_terms\":0},{\"additive_terms\":1,\"campaign\":0,\"discount_for_event\":0,\"extra_regressors_additive\":0,\"weekly\":1,\"yearly\":0,\"multiplicative_terms\":0},{\"additive_terms\":1,\"campaign\":0,\"discount_for_event\":0,\"extra_regressors_additive\":0,\"weekly\":1,\"yearly\":0,\"multiplicative_terms\":0},{\"additive_terms\":1,\"campaign\":0,\"discount_for_event\":0,\"extra_regressors_additive\":0,\"weekly\":1,\"yearly\":0,\"multiplicative_terms\":0},{\"additive_terms\":1,\"campaign\":0,\"discount_for_event\":0,\"extra_regressors_additive\":0,\"weekly\":1,\"yearly\":0,\"multiplicative_terms\":0},{\"additive_terms\":1,\"campaign\":0,\"discount_for_event\":0,\"extra_regressors_additive\":0,\"weekly\":1,\"yearly\":0,\"multiplicative_terms\":0},{\"additive_terms\":1,\"campaign\":0,\"discount_for_event\":0,\"extra_regressors_additive\":0,\"weekly\":1,\"yearly\":0,\"multiplicative_terms\":0},{\"additive_terms\":1,\"campaign\":0,\"discount_for_event\":0,\"extra_regressors_additive\":0,\"weekly\":1,\"yearly\":0,\"multiplicative_terms\":0},{\"additive_terms\":1,\"campaign\":0,\"discount_for_event\":0,\"extra_regressors_additive\":0,\"weekly\":1,\"yearly\":0,\"multiplicative_terms\":0},{\"additive_terms\":1,\"campaign\":0,\"discount_for_event\":0,\"extra_regressors_additive\":0,\"weekly\":1,\"yearly\":0,\"multiplicative_terms\":0},{\"additive_terms\":1,\"campaign\":0,\"discount_for_event\":0,\"extra_regressors_additive\":0,\"weekly\":1,\"yearly\":0,\"multiplicative_terms\":0},{\"additive_terms\":1,\"campaign\":0,\"discount_for_event\":0,\"extra_regressors_additive\":0,\"weekly\":1,\"yearly\":0,\"multiplicative_terms\":0},{\"additive_terms\":1,\"campaign\":0,\"discount_for_event\":0,\"extra_regressors_additive\":0,\"weekly\":1,\"yearly\":0,\"multiplicative_terms\":0},{\"additive_terms\":1,\"campaign\":0,\"discount_for_event\":0,\"extra_regressors_additive\":0,\"weekly\":1,\"yearly\":0,\"multiplicative_terms\":0},{\"additive_terms\":1,\"campaign\":0,\"discount_for_event\":0,\"extra_regressors_additive\":0,\"weekly\":1,\"yearly\":0,\"multiplicative_terms\":0},{\"additive_terms\":1,\"campaign\":0,\"discount_for_event\":0,\"extra_regressors_additive\":0,\"weekly\":1,\"yearly\":0,\"multiplicative_terms\":0},{\"additive_terms\":1,\"campaign\":0,\"discount_for_event\":0,\"extra_regressors_additive\":0,\"weekly\":1,\"yearly\":0,\"multiplicative_terms\":0},{\"additive_terms\":1,\"campaign\":0,\"discount_for_event\":0,\"extra_regressors_additive\":0,\"weekly\":1,\"yearly\":0,\"multiplicative_terms\":0},{\"additive_terms\":1,\"campaign\":0,\"discount_for_event\":0,\"extra_regressors_additive\":0,\"weekly\":1,\"yearly\":0,\"multiplicative_terms\":0},{\"additive_terms\":1,\"campaign\":0,\"discount_for_event\":0,\"extra_regressors_additive\":0,\"weekly\":1,\"yearly\":0,\"multiplicative_terms\":0},{\"additive_terms\":1,\"campaign\":0,\"discount_for_event\":0,\"extra_regressors_additive\":0,\"weekly\":1,\"yearly\":0,\"multiplicative_terms\":0},{\"additive_terms\":1,\"campaign\":0,\"discount_for_event\":0,\"extra_regressors_additive\":0,\"weekly\":1,\"yearly\":0,\"multiplicative_terms\":0},{\"additive_terms\":1,\"campaign\":0,\"discount_for_event\":0,\"extra_regressors_additive\":0,\"weekly\":1,\"yearly\":0,\"multiplicative_terms\":0},{\"additive_terms\":1,\"campaign\":0,\"discount_for_event\":0,\"extra_regressors_additive\":0,\"weekly\":1,\"yearly\":0,\"multiplicative_terms\":0},{\"additive_terms\":1,\"campaign\":0,\"discount_for_event\":0,\"extra_regressors_additive\":0,\"weekly\":1,\"yearly\":0,\"multiplicative_terms\":0},{\"additive_terms\":1,\"campaign\":0,\"discount_for_event\":0,\"extra_regressors_additive\":0,\"weekly\":1,\"yearly\":0,\"multiplicative_terms\":0},{\"additive_terms\":1,\"campaign\":0,\"discount_for_event\":0,\"extra_regressors_additive\":0,\"weekly\":1,\"yearly\":0,\"multiplicative_terms\":0},{\"additive_terms\":1,\"campaign\":0,\"discount_for_event\":0,\"extra_regressors_additive\":0,\"weekly\":1,\"yearly\":0,\"multiplicative_terms\":0},{\"additive_terms\":1,\"campaign\":0,\"discount_for_event\":0,\"extra_regressors_additive\":0,\"weekly\":1,\"yearly\":0,\"multiplicative_terms\":0},{\"additive_terms\":1,\"campaign\":0,\"discount_for_event\":0,\"extra_regressors_additive\":0,\"weekly\":1,\"yearly\":0,\"multiplicative_terms\":0},{\"additive_terms\":1,\"campaign\":1,\"discount_for_event\":0,\"extra_regressors_additive\":1,\"weekly\":0,\"yearly\":0,\"multiplicative_terms\":0},{\"additive_terms\":1,\"campaign\":0,\"discount_for_event\":1,\"extra_regressors_additive\":1,\"weekly\":0,\"yearly\":0,\"multiplicative_terms\":0}]}", "changepoints_t": [0.1889763779527559, 0.1968503937007874, 0.2047244094488189, 0.2125984251968504, 0.2204724409448819, 0.2283464566929134, 0.23622047244094488, 0.4251968503937008, 0.5905511811023622, 0.6062992125984252, 0.6141732283464567, 0.6220472440944882, 0.6299212598425197, 0.6377952755905512, 0.6614173228346457], "seasonalities": [["yearly", "weekly"], {"yearly": {"period": 365.25, "fourier_order": 10, "prior_scale": 10.0, "mode": "additive", "condition_name": null}, "weekly": {"period": 7, "fourier_order": 52, "prior_scale": 10.0, "mode": "additive", "condition_name": null}}], "extra_regressors": [["campaign", "discount_for_event"], {"campaign": {"prior_scale": 10.0, "standardize": "auto", "mu": 0.0, "std": 1.0, "mode": "additive"}, "discount_for_event": {"prior_scale": 10.0, "standardize": "auto", "mu": 0.0, "std": 1.0, "mode": "additive"}}], "fit_kwargs": {}, "params": {"lp__": [[24.391]], "k": [[0.156984]], "m": [[0.0210673]], "delta": [[-6.08955e-11, 3.86582e-11, -9.01509e-11, 6.40406e-11, 8.37234e-11, -8.99654e-11, -3.99743e-11, 1.86624e-12, -1.7412e-11, 3.1816e-11, 5.83959e-11, 5.29343e-11, -8.45579e-11, 4.58902e-11, 8.79638e-11]], "sigma_obs": [[0.179223]], "beta": [[-0.344896, 0.223325, 0.218711, -1.02384, 0.547065, 0.275955, -0.307684, -0.0844708, -0.900812, -0.4758, 0.767917, -0.468793, -0.209627, 0.878966, -0.127769, 1.46929, 0.22377, -0.921992, -0.287941, -0.677482, -0.00796008, -0.0165293, 0.0143436, 0.0114386, -0.0178861, -0.0040824, 0.0178861, -0.00408239, -0.0143436, 0.0114386, 0.00796008, -0.0165293, -2.44216e-09, 0.0183461, -0.00796007, -0.0165293, 0.0143436, 0.0114386, -0.0178861, -0.00408239, 0.0178861, -0.0040824, -0.0143436, 0.0114386, 0.00796009, -0.0165293, -4.8238e-09, 0.0183461, -0.00796009, -0.0165293, 0.0143436, 0.0114386, -0.0178861, -0.00408245, 0.0178861, -0.00408247, -0.0143436, 0.0114386, 0.00796008, -0.0165293, -3.76083e-09, 0.0183461, -0.00796009, -0.0165293, 0.0143436, 0.0114386, -0.0178861, -0.0040824, 0.0178861, -0.00408238, -0.0143436, 0.0114386, 0.00796008, -0.0165293, -9.78053e-09, 0.0183461, -0.00796003, -0.0165293, 0.0143436, 0.0114386, -0.0178862, -0.00408231, 0.0178862, -0.00408233, -0.0143436, 0.0114386, 0.00796019, -0.0165292, -1.36346e-08, 0.0183461, -0.00796022, -0.0165292, 0.0143437, 0.0114385, -0.0178862, -0.00408232, 0.0178861, -0.00408242, -0.0143436, 0.0114386, 0.00796017, -0.0165292, -7.55307e-09, 0.0183461, -0.00796024, -0.0165292, 0.0143436, 0.0114386, -0.0178861, -0.00408261, 0.0178861, -0.00408241, -0.0143436, 0.0114386, 0.00796009, -0.0165293, 9.79359e-09, 0.0183461, -0.00796005, -0.0165293, 0.0143436, 0.0114386, -0.0178861, -0.00408243, 0.0615889, 1.68367e-13]], "trend": [[0.0210673, 0.0507335, 0.0519696, 0.0532057, 0.0544418, 0.0556779, 0.056914, 0.0581501, 0.0878164, 0.113774, 0.116247, 0.117483, 0.118719, 0.119955, 0.121191, 0.124899, 0.142205, 0.147149, 0.148385, 0.178051]]}, "__prophet_version": "1.1.5"}