{"growth": "linear", "n_changepoints": 16, "specified_changepoints": false, "changepoint_range": 0.8, "yearly_seasonality": "auto", "weekly_seasonality": 52, "daily_seasonality": "auto", "seasonality_mode": "additive", "seasonality_prior_scale": 10.0, "changepoint_prior_scale": 0.05, "holidays_prior_scale": 10.0, "mcmc_samples": 0, "interval_width": 0.8, "uncertainty_samples": 1000, "y_scale": 5.0, "y_min": 0.0, "scaling": "absmax", "logistic_floor": false, "country_holidays": null, "component_modes": {"additive": ["yearly", "weekly", "campaign", "discount_for_event", "additive_terms", "extra_regressors_additive", "holidays"], "multiplicative": ["multiplicative_terms", "extra_regressors_multiplicative"]}, "holidays_mode": "additive", "changepoints": "{\"name\":\"ds\",\"index\":[1,2,3,4,5,6,7,8,9,10,11,12,13,14,15,16],\"data\":[\"2018-07-23T00:00:00.000\",\"2018-08-06T00:00:00.000\",\"2018-08-13T00:00:00.000\",\"2018-08-27T00:00:00.000\",\"2018-09-03T00:00:00.000\",\"2018-11-05T00:00:00.000\",\"2018-12-17T00:00:00.000\",\"2019-01-21T00:00:00.000\",\"2019-01-28T00:00:00.000\",\"2019-07-15T00:00:00.000\",\"2019-07-22T00:00:00.000\",\"2019-07-29T00:00:00.000\",\"2019-08-05T00:00:00.000\",\"2019-08-12T00:00:00.000\",\"2019-08-19T00:00:00.000\",\"2019-08-26T00:00:00.000\"]}", "history_dates": "{\"name\":\"ds\",\"index\":[0,1,2,3,4,5,6,7,8,9,10,11,12,13,14,15,16,17,18,19,20,21],\"data\":[\"2018-03-26T00:00:00.000\",\"2018-07-23T00:00:00.000\",\"2018-08-06T00:00:00.000\",\"2018-08-13T00:00:00.000\",\"2018-08-27T00:00:00.000\",\"2018-09-03T00:00:00.000\",\"2018-11-05T00:00:00.000\",\"2018-12-17T00:00:00.000\",\"2019-01-21T00:00:00.000\",\"2019-01-28T00:00:00.000\",\"2019-07-15T00:00:00.000\",\"2019-07-22T00:00:00.000\",\"2019-07-29T00:00:00.000\",\"2019-08-05T00:00:00.000\",\"2019-08-12T00:00:00.000\",\"2019-08-19T00:00:00.000\",\"2019-08-26T00:00:00.000\",\"2019-09-02T00:00:00.000\",\"2020-06-22T00:00:00.000\",\"2021-04-12T00:00:00.000\",\"2021-07-12T00:00:00.000\",\"2021-10-25T00:00:00.000\"]}", "train_holiday_names": null, "start": 1522022400.0, "t_scale": 113097600.0, "holidays": null, "history": "{\"schema\":{\"fields\":[{\"name\":\"ds\",\"type\":\"datetime\"},{\"name\":\"y\",\"type\":\"integer\"},{\"name\":\"campaign\",\"type\":\"number\"},{\"name\":\"discount_for_event\",\"type\":\"number\"},{\"name\":\"floor\",\"type\":\"number\"},{\"name\":\"t\",\"type\":\"number\"},{\"name\":\"y_scaled\",\"type\":\"number\"}],\"pandas_version\":\"1.4.0\"},\"data\":[{\"ds\":\"2018-03-26T00:00:00.000\",\"y\":1,\"campaign\":1.0,\"discount_for_event\":0.0,\"floor\":0.0,\"t\":0.0,\"y_scaled\":0.2},{\"ds\":\"2018-07-23T00:00:00.000\",\"y\":1,\"campaign\":0.0,\"discount_for_event\":0.0,\"floor\":0.0,\"t\":0.0909090909,\"y_scaled\":0.2},{\"ds\":\"2018-08-06T00:00:00.000\",\"y\":2,\"campaign\":1.0,\"discount_for_event\":0.0,\"floor\":0.0,\"t\":0.1016042781,\"y_scaled\":0.4},{\"ds\":\"2018-08-13T00:00:00.000\",\"y\":2,\"campaign\":1.0,\"discount_for_event\":0.0,\"floor\":0.0,\"t\":0.1069518717,\"y_scaled\":0.4},{\"ds\":\"2018-08-27T00:00:00.000\",\"y\":4,\"campaign\":0.0,\"discount_for_event\":0.0,\"floor\":0.0,\"t\":0.1176470588,\"y_scaled\":0.8},{\"ds\":\"2018-09-03T00:00:00.000\",\"y\":1,\"campaign\":0.0,\"discount_for_event\":0.0,\"floor\":0.0,\"t\":0.1229946524,\"y_scaled\":0.2},{\"ds\":\"2018-11-05T00:00:00.000\",\"y\":1,\"campaign\":0.0,\"discount_for_event\":0.0,\"floor\":0.0,\"t\":0.1711229947,\"y_scaled\":0.2},{\"ds\":\"2018-12-17T00:00:00.000\",\"y\":1,\"campaign\":0.0,\"discount_for_event\":0.0,\"floor\":0.0,\"t\":0.2032085561,\"y_scaled\":0.2},{\"ds\":\"2019-01-21T00:00:00.000\",\"y\":1,\"campaign\":1.0,\"discount_for_event\":0.0,\"floor\":0.0,\"t\":0.2299465241,\"y_scaled\":0.2},{\"ds\":\"2019-01-28T00:00:00.000\",\"y\":1,\"campaign\":1.0,\"discount_for_event\":0.0,\"floor\":0.0,\"t\":0.2352941176,\"y_scaled\":0.2},{\"ds\":\"2019-07-15T00:00:00.000\",\"y\":1,\"campaign\":1.0,\"discount_for_event\":0.0,\"floor\":0.0,\"t\":0.3636363636,\"y_scaled\":0.2},{\"ds\":\"2019-07-22T00:00:00.000\",\"y\":4,\"campaign\":1.0,\"discount_for_event\":0.0,\"floor\":0.0,\"t\":0.3689839572,\"y_scaled\":0.8},{\"ds\":\"2019-07-29T00:00:00.000\",\"y\":1,\"campaign\":1.0,\"discount_for_event\":0.0,\"floor\":0.0,\"t\":0.3743315508,\"y_scaled\":0.2},{\"ds\":\"2019-08-05T00:00:00.000\",\"y\":4,\"campaign\":0.0,\"discount_for_event\":0.0,\"floor\":0.0,\"t\":0.3796791444,\"y_scaled\":0.8},{\"ds\":\"2019-08-12T00:00:00.000\",\"y\":3,\"campaign\":0.0,\"discount_for_event\":0.0,\"floor\":0.0,\"t\":0.385026738,\"y_scaled\":0.6},{\"ds\":\"2019-08-19T00:00:00.000\",\"y\":5,\"campaign\":1.0,\"discount_for_event\":0.0,\"floor\":0.0,\"t\":0.3903743316,\"y_scaled\":1.0},{\"ds\":\"2019-08-26T00:00:00.000\",\"y\":2,\"campaign\":1.0,\"discount_for_event\":0.0,\"floor\":0.0,\"t\":0.3957219251,\"y_scaled\":0.4},{\"ds\":\"2019-09-02T00:00:00.000\",\"y\":1,\"campaign\":1.0,\"discount_for_event\":0.0,\"floor\":0.0,\"t\":0.4010695187,\"y_scaled\":0.2},{\"ds\":\"2020-06-22T00:00:00.000\",\"y\":1,\"campaign\":0.0,\"discount_for_event\":0.0,\"floor\":0.0,\"t\":0.6256684492,\"y_scaled\":0.2},{\"ds\":\"2021-04-12T00:00:00.000\",\"y\":1,\"campaign\":0.0,\"discount_for_event\":0.0,\"floor\":0.0,\"t\":0.8502673797,\"y_scaled\":0.2},{\"ds\":\"2021-07-12T00:00:00.000\",\"y\":1,\"campaign\":1.0,\"discount_for_event\":0.0,\"floor\":0.0,\"t\":0.9197860963,\"y_scaled\":0.2},{\"ds\":\"2021-10-25T00:00:00.000\",\"y\":1,\"campaign\":1.0,\"discount_for_event\":0.0,\"floor\":0.0,\"t\":1.0,\"y_scaled\":0.2}]}", "train_component_cols": "{\"schema\":{\"fields\":[{\"name\":\"additive_terms\",\"type\":\"integer\"},{\"name\":\"campaign\",\"type\":\"integer\"},{\"name\":\"discount_for_event\",\"type\":\"integer\"},{\"name\":\"extra_regressors_additive\",\"type\":\"integer\"},{\"name\":\"weekly\",\"type\":\"integer\"},{\"name\":\"yearly\",\"type\":\"integer\"},{\"name\":\"multiplicative_terms\",\"type\":\"integer\"}],\"pandas_version\":\"1.4.0\"},\"data\":[{\"additive_terms\":1,\"campaign\":0,\"discount_for_event\":0,\"extra_regressors_additive\":0,\"weekly\":0,\"yearly\":1,\"multiplicative_terms\":0},{\"additive_terms\":1,\"campaign\":0,\"discount_for_event\":0,\"extra_regressors_additive\":0,\"weekly\":0,\"yearly\":1,\"multiplicative_terms\":0},{\"additive_terms\":1,\"campaign\":0,\"discount_for_event\":0,\"extra_regressors_additive\":0,\"weekly\":0,\"yearly\":1,\"multiplicative_terms\":0},{\"additive_terms\":1,\"campaign\":0,\"discount_for_event\":0,\"extra_regressors_additive\":0,\"weekly\":0,\"yearly\":1,\"multiplicative_terms\":0},{\"additive_terms\":1,\"campaign\":0,\"discount_for_event\":0,\"extra_regressors_additive\":0,\"weekly\":0,\"yearly\":1,\"multiplicative_terms\":0},{\"additive_terms\":1,\"campaign\":0,\"discount_for_event\":0,\"extra_regressors_additive\":0,\"weekly\":0,\"yearly\":1,\"multiplicative_terms\":0},{\"additive_terms\":1,\"campaign\":0,\"discount_for_event\":0,\"extra_regressors_additive\":0,\"weekly\":0,\"yearly\":1,\"multiplicative_terms\":0},{\"additive_terms\":1,\"campaign\":0,\"discount_for_event\":0,\"extra_regressors_additive\":0,\"weekly\":0,\"yearly\":1,\"multiplicative_terms\":0},{\"additive_terms\":1,\"campaign\":0,\"discount_for_event\":0,\"extra_regressors_additive\":0,\"weekly\":0,\"yearly\":1,\"multiplicative_terms\":0},{\"additive_terms\":1,\"campaign\":0,\"discount_for_event\":0,\"extra_regressors_additive\":0,\"weekly\":0,\"yearly\":1,\"multiplicative_terms\":0},{\"additive_terms\":1,\"campaign\":0,\"discount_for_event\":0,\"extra_regressors_additive\":0,\"weekly\":0,\"yearly\":1,\"multiplicative_terms\":0},{\"additive_terms\":1,\"campaign\":0,\"discount_for_event\":0,\"extra_regressors_additive\":0,\"weekly\":0,\"yearly\":1,\"multiplicative_terms\":0},{\"additive_terms\":1,\"campaign\":0,\"discount_for_event\":0,\"extra_regressors_additive\":0,\"weekly\":0,\"yearly\":1,\"multiplicative_terms\":0},{\"additive_terms\":1,\"campaign\":0,\"discount_for_event\":0,\"extra_regressors_additive\":0,\"weekly\":0,\"yearly\":1,\"multiplicative_terms\":0},{\"additive_terms\":1,\"campaign\":0,\"discount_for_event\":0,\"extra_regressors_additive\":0,\"weekly\":0,\"yearly\":1,\"multiplicative_terms\":0},{\"additive_terms\":1,\"campaign\":0,\"discount_for_event\":0,\"extra_regressors_additive\":0,\"weekly\":0,\"yearly\":1,\"multiplicative_terms\":0},{\"additive_terms\":1,\"campaign\":0,\"discount_for_event\":0,\"extra_regressors_additive\":0,\"weekly\":0,\"yearly\":1,\"multiplicative_terms\":0},{\"additive_terms\":1,\"campaign\":0,\"discount_for_event\":0,\"extra_regressors_additive\":0,\"weekly\":0,\"yearly\":1,\"multiplicative_terms\":0},{\"additive_terms\":1,\"campaign\":0,\"discount_for_event\":0,\"extra_regressors_additive\":0,\"weekly\":0,\"yearly\":1,\"multiplicative_terms\":0},{\"additive_terms\":1,\"campaign\":0,\"discount_for_event\":0,\"extra_regressors_additive\":0,\"weekly\":0,\"yearly\":1,\"multiplicative_terms\":0},{\"additive_terms\":1,\"campaign\":0,\"discount_for_event\":0,\"extra_regressors_additive\":0,\"weekly\":1,\"yearly\":0,\"multiplicative_terms\":0},{\"additive_terms\":1,\"campaign\":0,\"discount_for_event\":0,\"extra_regressors_additive\":0,\"weekly\":1,\"yearly\":0,\"multiplicative_terms\":0},{\"additive_terms\":1,\"campaign\":0,\"discount_for_event\":0,\"extra_regressors_additive\":0,\"weekly\":1,\"yearly\":0,\"multiplicative_terms\":0},{\"additive_terms\":1,\"campaign\":0,\"discount_for_event\":0,\"extra_regressors_additive\":0,\"weekly\":1,\"yearly\":0,\"multiplicative_terms\":0},{\"additive_terms\":1,\"campaign\":0,\"discount_for_event\":0,\"extra_regressors_additive\":0,\"weekly\":1,\"yearly\":0,\"multiplicative_terms\":0},{\"additive_terms\":1,\"campaign\":0,\"discount_for_event\":0,\"extra_regressors_additive\":0,\"weekly\":1,\"yearly\":0,\"multiplicative_terms\":0},{\"additive_terms\":1,\"campaign\":0,\"discount_for_event\":0,\"extra_regressors_additive\":0,\"weekly\":1,\"yearly\":0,\"multiplicative_terms\":0},{\"additive_terms\":1,\"campaign\":0,\"discount_for_event\":0,\"extra_regressors_additive\":0,\"weekly\":1,\"yearly\":0,\"multiplicative_terms\":0},{\"additive_terms\":1,\"campaign\":0,\"discount_for_event\":0,\"extra_regressors_additive\":0,\"weekly\":1,\"yearly\":0,\"multiplicative_terms\":0},{\"additive_terms\":1,\"campaign\":0,\"discount_for_event\":0,\"extra_regressors_additive\":0,\"weekly\":1,\"yearly\":0,\"multiplicative_terms\":0},{\"additive_terms\":1,\"campaign\":0,\"discount_for_event\":0,\"extra_regressors_additive\":0,\"weekly\":1,\"yearly\":0,\"multiplicative_terms\":0},{\"additive_terms\":1,\"campaign\":0,\"discount_for_event\":0,\"extra_regressors_additive\":0,\"weekly\":1,\"yearly\":0,\"multiplicative_terms\":0},{\"additive_terms\":1,\"campaign\":0,\"discount_for_event\":0,\"extra_regressors_additive\":0,\"weekly\":1,\"yearly\":0,\"multiplicative_terms\":0},{\"additive_terms\":1,\"campaign\":0,\"discount_for_event\":0,\"extra_regressors_additive\":0,\"weekly\":1,\"yearly\":0,\"multiplicative_terms\":0},{\"additive_terms\":1,\"campaign\":0,\"discount_for_event\":0,\"extra_regressors_additive\":0,\"weekly\":1,\"yearly\":0,\"multiplicative_terms\":0},{\"additive_terms\":1,\"campaign\":0,\"discount_for_event\":0,\"extra_regressors_additive\":0,\"weekly\":1,\"yearly\":0,\"multiplicative_terms\":0},{\"additive_terms\":1,\"campaign\":0,\"discount_for_event\":0,\"extra_regressors_additive\":0,\"weekly\":1,\"yearly\":0,\"multiplicative_terms\":0},{\"additive_terms\":1,\"campaign\":0,\"discount_for_event\":0,\"extra_regressors_additive\":0,\"weekly\":1,\"yearly\":0,\"multiplicative_terms\":0},{\"additive_terms\":1,\"campaign\":0,\"discount_for_event\":0,\"extra_regressors_additive\":0,\"weekly\":1,\"yearly\":0,\"multiplicative_terms\":0},{\"additive_terms\":1,\"campaign\":0,\"discount_for_event\":0,\"extra_regressors_additive\":0,\"weekly\":1,\"yearly\":0,\"multiplicative_terms\":0},{\"additive_terms\":1,\"campaign\":0,\"discount_for_event\":0,\"extra_regressors_additive\":0,\"weekly\":1,\"yearly\":0,\"multiplicative_terms\":0},{\"additive_terms\":1,\"campaign\":0,\"discount_for_event\":0,\"extra_regressors_additive\":0,\"weekly\":1,\"yearly\":0,\"multiplicative_terms\":0},{\"additive_terms\":1,\"campaign\":0,\"discount_for_event\":0,\"extra_regressors_additive\":0,\"weekly\":1,\"yearly\":0,\"multiplicative_terms\":0},{\"additive_terms\":1,\"campaign\":0,\"discount_for_event\":0,\"extra_regressors_additive\":0,\"weekly\":1,\"yearly\":0,\"multiplicative_terms\":0},{\"additive_terms\":1,\"campaign\":0,\"discount_for_event\":0,\"extra_regressors_additive\":0,\"weekly\":1,\"yearly\":0,\"multiplicative_terms\":0},{\"additive_terms\":1,\"campaign\":0,\"discount_for_event\":0,\"extra_regressors_additive\":0,\"weekly\":1,\"yearly\":0,\"multiplicative_terms\":0},{\"additive_terms\":1,\"campaign\":0,\"discount_for_event\":0,\"extra_regressors_additive\":0,\"weekly\":1,\"yearly\":0,\"multiplicative_terms\":0},{\"additive_terms\":1,\"campaign\":0,\"discount_for_event\":0,\"extra_regressors_additive\":0,\"weekly\":1,\"yearly\":0,\"multiplicative_terms\":0},{\"additive_terms\":1,\"campaign\":0,\"discount_for_event\":0,\"extra_regressors_additive\":0,\"weekly\":1,\"yearly\":0,\"multiplicative_terms\":0},{\"additive_terms\":1,\"campaign\":0,\"discount_for_event\":0,\"extra_regressors_additive\":0,\"weekly\":1,\"yearly\":0,\"multiplicative_terms\":0},{\"additive_terms\":1,\"campaign\":0,\"discount_for_event\":0,\"extra_regressors_additive\":0,\"weekly\":1,\"yearly\":0,\"multiplicative_terms\":0},{\"additive_terms\":1,\"campaign\":0,\"discount_for_event\":0,\"extra_regressors_additive\":0,\"weekly\":1,\"yearly\":0,\"multiplicative_terms\":0},{\"additive_terms\":1,\"campaign\":0,\"discount_for_event\":0,\"extra_regressors_additive\":0,\"weekly\":1,\"yearly\":0,\"multiplicative_terms\":0},{\"additive_terms\":1,\"campaign\":0,\"discount_for_event\":0,\"extra_regressors_additive\":0,\"weekly\":1,\"yearly\":0,\"multiplicative_terms\":0},{\"additive_terms\":1,\"campaign\":0,\"discount_for_event\":0,\"extra_regressors_additive\":0,\"weekly\":1,\"yearly\":0,\"multiplicative_terms\":0},{\"additive_terms\":1,\"campaign\":0,\"discount_for_event\":0,\"extra_regressors_additive\":0,\"weekly\":1,\"yearly\":0,\"multiplicative_terms\":0},{\"additive_terms\":1,\"campaign\":0,\"discount_for_event\":0,\"extra_regressors_additive\":0,\"weekly\":1,\"yearly\":0,\"multiplicative_terms\":0},{\"additive_terms\":1,\"campaign\":0,\"discount_for_event\":0,\"extra_regressors_additive\":0,\"weekly\":1,\"yearly\":0,\"multiplicative_terms\":0},{\"additive_terms\":1,\"campaign\":0,\"discount_for_event\":0,\"extra_regressors_additive\":0,\"weekly\":1,\"yearly\":0,\"multiplicative_terms\":0},{\"additive_terms\":1,\"campaign\":0,\"discount_for_event\":0,\"extra_regressors_additive\":0,\"weekly\":1,\"yearly\":0,\"multiplicative_terms\":0},{\"additive_terms\":1,\"campaign\":0,\"discount_for_event\":0,\"extra_regressors_additive\":0,\"weekly\":1,\"yearly\":0,\"multiplicative_terms\":0},{\"additive_terms\":1,\"campaign\":0,\"discount_for_event\":0,\"extra_regressors_additive\":0,\"weekly\":1,\"yearly\":0,\"multiplicative_terms\":0},{\"additive_terms\":1,\"campaign\":0,\"discount_for_event\":0,\"extra_regressors_additive\":0,\"weekly\":1,\"yearly\":0,\"multiplicative_terms\":0},{\"additive_terms\":1,\"campaign\":0,\"discount_for_event\":0,\"extra_regressors_additive\":0,\"weekly\":1,\"yearly\":0,\"multiplicative_terms\":0},{\"additive_terms\":1,\"campaign\":0,\"discount_for_event\":0,\"extra_regressors_additive\":0,\"weekly\":1,\"yearly\":0,\"multiplicative_terms\":0},{\"additive_terms\":1,\"campaign\":0,\"discount_for_event\":0,\"extra_regressors_additive\":0,\"weekly\":1,\"yearly\":0,\"multiplicative_terms\":0},{\"additive_terms\":1,\"campaign\":0,\"discount_for_event\":0,\"extra_regressors_additive\":0,\"weekly\":1,\"yearly\":0,\"multiplicative_terms\":0},{\"additive_terms\":1,\"campaign\":0,\"discount_for_event\":0,\"extra_regressors_additive\":0,\"weekly\":1,\"yearly\":0,\"multiplicative_terms\":0},{\"additive_terms\":1,\"campaign\":0,\"discount_for_event\":0,\"extra_regressors_additive\":0,\"weekly\":1,\"yearly\":0,\"multiplicative_terms\":0},{\"additive_terms\":1,\"campaign\":0,\"discount_for_event\":0,\"extra_regressors_additive\":0,\"weekly\":1,\"yearly\":0,\"multiplicative_terms\":0},{\"additive_terms\":1,\"campaign\":0,\"discount_for_event\":0,\"extra_regressors_additive\":0,\"weekly\":1,\"yearly\":0,\"multiplicative_terms\":0},{\"additive_terms\":1,\"campaign\":0,\"discount_for_event\":0,\"extra_regressors_additive\":0,\"weekly\":1,\"yearly\":0,\"multiplicative_terms\":0},{\"additive_terms\":1,\"campaign\":0,\"discount_for_event\":0,\"extra_regressors_additive\":0,\"weekly\":1,\"yearly\":0,\"multiplicative_terms\":0},{\"additive_terms\":1,\"campaign\":0,\"discount_for_event\":0,\"extra_regressors_additive\":0,\"weekly\":1,\"yearly\":0,\"multiplicative_terms\":0},{\"additive_terms\":1,\"campaign\":0,\"discount_for_event\":0,\"extra_regressors_additive\":0,\"weekly\":1,\"yearly\":0,\"multiplicative_terms\":0},{\"additive_terms\":1,\"campaign\":0,\"discount_for_event\":0,\"extra_regressors_additive\":0,\"weekly\":1,\"yearly\":0,\"multiplicative_terms\":0},{\"additive_terms\":1,\"campaign\":0,\"discount_for_event\":0,\"extra_regressors_additive\":0,\"weekly\":1,\"yearly\":0,\"multiplicative_terms\":0},{\"additive_terms\":1,\"campaign\":0,\"discount_for_event\":0,\"extra_regressors_additive\":0,\"weekly\":1,\"yearly\":0,\"multiplicative_terms\":0},{\"additive_terms\":1,\"campaign\":0,\"discount_for_event\":0,\"extra_regressors_additive\":0,\"weekly\":1,\"yearly\":0,\"multiplicative_terms\":0},{\"additive_terms\":1,\"campaign\":0,\"discount_for_event\":0,\"extra_regressors_additive\":0,\"weekly\":1,\"yearly\":0,\"multiplicative_terms\":0},{\"additive_terms\":1,\"campaign\":0,\"discount_for_event\":0,\"extra_regressors_additive\":0,\"weekly\":1,\"yearly\":0,\"multiplicative_terms\":0},{\"additive_terms\":1,\"campaign\":0,\"discount_for_event\":0,\"extra_regressors_additive\":0,\"weekly\":1,\"yearly\":0,\"multiplicative_terms\":0},{\"additive_terms\":1,\"campaign\":0,\"discount_for_event\":0,\"extra_regressors_additive\":0,\"weekly\":1,\"yearly\":0,\"multiplicative_terms\":0},{\"additive_terms\":1,\"campaign\":0,\"discount_for_event\":0,\"extra_regressors_additive\":0,\"weekly\":1,\"yearly\":0,\"multiplicative_terms\":0},{\"additive_terms\":1,\"campaign\":0,\"discount_for_event\":0,\"extra_regressors_additive\":0,\"weekly\":1,\"yearly\":0,\"multiplicative_terms\":0},{\"additive_terms\":1,\"campaign\":0,\"discount_for_event\":0,\"extra_regressors_additive\":0,\"weekly\":1,\"yearly\":0,\"multiplicative_terms\":0},{\"additive_terms\":1,\"campaign\":0,\"discount_for_event\":0,\"extra_regressors_additive\":0,\"weekly\":1,\"yearly\":0,\"multiplicative_terms\":0},{\"additive_terms\":1,\"campaign\":0,\"discount_for_event\":0,\"extra_regressors_additive\":0,\"weekly\":1,\"yearly\":0,\"multiplicative_terms\":0},{\"additive_terms\":1,\"campaign\":0,\"discount_for_event\":0,\"extra_regressors_additive\":0,\"weekly\":1,\"yearly\":0,\"multiplicative_terms\":0},{\"additive_terms\":1,\"campaign\":0,\"discount_for_event\":0,\"extra_regressors_additive\":0,\"weekly\":1,\"yearly\":0,\"multiplicative_terms\":0},{\"additive_terms\":1,\"campaign\":0,\"discount_for_event\":0,\"extra_regressors_additive\":0,\"weekly\":1,\"yearly\":0,\"multiplicative_terms\":0},{\"additive_terms\":1,\"campaign\":0,\"discount_for_event\":0,\"extra_regressors_additive\":0,\"weekly\":1,\"yearly\":0,\"multiplicative_terms\":0},{\"additive_terms\":1,\"campaign\":0,\"discount_for_event\":0,\"extra_regressors_additive\":0,\"weekly\":1,\"yearly\":0,\"multiplicative_terms\":0},{\"additive_terms\":1,\"campaign\":0,\"discount_for_event\":0,\"extra_regressors_additive\":0,\"weekly\":1,\"yearly\":0,\"multiplicative_terms\":0},{\"additive_terms\":1,\"campaign\":0,\"discount_for_event\":0,\"extra_regressors_additive\":0,\"weekly\":1,\"yearly\":0,\"multiplicative_terms\":0},{\"additive_terms\":1,\"campaign\":0,\"discount_for_event\":0,\"extra_regressors_additive\":0,\"weekly\":1,\"yearly\":0,\"multiplicative_terms\":0},{\"additive_terms\":1,\"campaign\":0,\"discount_for_event\":0,\"extra_regressors_additive\":0,\"weekly\":1,\"yearly\":0,\"multiplicative_terms\":0},{\"additive_terms\":1,\"campaign\":0,\"discount_for_event\":0,\"extra_regressors_additive\":0,\"weekly\":1,\"yearly\":0,\"multiplicative_terms\":0},{\"additive_terms\":1,\"campaign\":0,\"discount_for_event\":0,\"extra_regressors_additive\":0,\"weekly\":1,\"yearly\":0,\"multiplicative_terms\":0},{\"additive_terms\":1,\"campaign\":0,\"discount_for_event\":0,\"extra_regressors_additive\":0,\"weekly\":1,\"yearly\":0,\"multiplicative_terms\":0},{\"additive_terms\":1,\"campaign\":0,\"discount_for_event\":0,\"extra_regressors_additive\":0,\"weekly\":1,\"yearly\":0,\"multiplicative_terms\":0},{\"additive_terms\":1,\"campaign\":0,\"discount_for_event\":0,\"extra_regressors_additive\":0,\"weekly\":1,\"yearly\":0,\"multiplicative_terms\":0},{\"additive_terms\":1,\"campaign\":0,\"discount_for_event\":0,\"extra_regressors_additive\":0,\"weekly\":1,\"yearly\":0,\"multiplicative_terms\":0},{\"additive_terms\":1,\"campaign\":0,\"discount_for_event\":0,\"extra_regressors_additive\":0,\"weekly\":1,\"yearly\":0,\"multiplicative_terms\":0},{\"additive_terms\":1,\"campaign\":0,\"discount_for_event\":0,\"extra_regressors_additive\":0,\"weekly\":1,\"yearly\":0,\"multiplicative_terms\":0},{\"additive_terms\":1,\"campaign\":0,\"discount_for_event\":0,\"extra_regressors_additive\":0,\"weekly\":1,\"yearly\":0,\"multiplicative_terms\":0},{\"additive_terms\":1,\"campaign\":0,\"discount_for_event\":0,\"extra_regressors_additive\":0,\"weekly\":1,\"yearly\":0,\"multiplicative_terms\":0},{\"additive_terms\":1,\"campaign\":0,\"discount_for_event\":0,\"extra_regressors_additive\":0,\"weekly\":1,\"yearly\":0,\"multiplicative_terms\":0},{\"additive_terms\":1,\"campaign\":0,\"discount_for_event\":0,\"extra_regressors_additive\":0,\"weekly\":1,\"yearly\":0,\"multiplicative_terms\":0},{\"additive_terms\":1,\"campaign\":0,\"discount_for_event\":0,\"extra_regressors_additive\":0,\"weekly\":1,\"yearly\":0,\"multiplicative_terms\":0},{\"additive_terms\":1,\"campaign\":0,\"discount_for_event\":0,\"extra_regressors_additive\":0,\"weekly\":1,\"yearly\":0,\"multiplicative_terms\":0},{\"additive_terms\":1,\"campaign\":0,\"discount_for_event\":0,\"extra_regressors_additive\":0,\"weekly\":1,\"yearly\":0,\"multiplicative_terms\":0},{\"additive_terms\":1,\"campaign\":0,\"discount_for_event\":0,\"extra_regressors_additive\":0,\"weekly\":1,\"yearly\":0,\"multiplicative_terms\":0},{\"additive_terms\":1,\"campaign\":0,\"discount_for_event\":0,\"extra_regressors_additive\":0,\"weekly\":1,\"yearly\":0,\"multiplicative_terms\":0},{\"additive_terms\":1,\"campaign\":0,\"discount_for_event\":0,\"extra_regressors_additive\":0,\"weekly\":1,\"yearly\":0,\"multiplicative_terms\":0},{\"additive_terms\":1,\"campaign\":0,\"discount_for_event\":0,\"extra_regressors_additive\":0,\"weekly\":1,\"yearly\":0,\"multiplicative_terms\":0},{\"additive_terms\":1,\"campaign\":0,\"discount_for_event\":0,\"extra_regressors_additive\":0,\"weekly\":1,\"yearly\":0,\"multiplicative_terms\":0},{\"additive_terms\":1,\"campaign\":0,\"discount_for_event\":0,\"extra_regressors_additive\":0,\"weekly\":1,\"yearly\":0,\"multiplicative_terms\":0},{\"additive_terms\":1,\"campaign\":0,\"discount_for_event\":0,\"extra_regressors_additive\":0,\"weekly\":1,\"yearly\":0,\"multiplicative_terms\":0},{\"additive_terms\":1,\"campaign\":0,\"discount_for_event\":0,\"extra_regressors_additive\":0,\"weekly\":1,\"yearly\":0,\"multiplicative_terms\":0},{\"additive_terms\":1,\"campaign\":0,\"discount_for_event\":0,\"extra_regressors_additive\":0,\"weekly\":1,\"yearly\":0,\"multiplicative_terms\":0},{\"additive_terms\":1,\"campaign\":0,\"discount_for_event\":0,\"extra_regressors_additive\":0,\"weekly\":1,\"yearly\":0,\"multiplicative_terms\":0},{\"additive_terms\":1,\"campaign\":0,\"discount_for_event\":0,\"extra_regressors_additive\":0,\"weekly\":1,\"yearly\":0,\"multiplicative_terms\":0},{\"additive_terms\":1,\"campaign\":0,\"discount_for_event\":0,\"extra_regressors_additive\":0,\"weekly\":1,\"yearly\":0,\"multiplicative_terms\":0},{\"additive_terms\":1,\"campaign\":1,\"discount_for_event\":0,\"extra_regressors_additive\":1,\"weekly\":0,\"yearly\":0,\"multiplicative_terms\":0},{\"additive_terms\":1,\"campaign\":0,\"discount_for_event\":1,\"extra_regressors_additive\":1,\"weekly\":0,\"yearly\":0,\"multiplicative_terms\":0}]}", "changepoints_t": [0.09090909090909091, 0.10160427807486631, 0.10695187165775401, 0.11764705882352941, 0.12299465240641712, 0.1711229946524064, 0.20320855614973263, 0.22994652406417113, 0.23529411764705882, 0.36363636363636365, 0.3689839572192513, 0.37433155080213903, 0.37967914438502676, 0.3850267379679144, 0.39037433155080214, 0.39572192513368987], "seasonalities": [["yearly", "weekly"], {"yearly": {"period": 365.25, "fourier_order": 10, "prior_scale": 10.0, "mode": "additive", "condition_name": null}, "weekly": {"period": 7, "fourier_order": 52, "prior_scale": 10.0, "mode": "additive", "condition_name": null}}], "extra_regressors": [["campaign", "discount_for_event"], {"campaign": {"prior_scale": 10.0, "standardize": "auto", "mu": 0.0, "std": 1.0, "mode": "additive"}, "discount_for_event": {"prior_scale": 10.0, "standardize": "auto", "mu": 0.0, "std": 1.0, "mode": "additive"}}], "fit_kwargs": {}, "params": {"lp__": [[31.0044]], "k": [[0.606464]], "m": [[0.0113888]], "delta": [[-4.63396e-09, 5.10454e-09, 1.17422e-08, 1.69894e-09, -9.94748e-10, 3.61707e-09, 9.44297e-09, 4.2054e-09, -9.4832e-09, -4.66581e-09, -9.81273e-09, -2.53959e-09, 1.13206e-08, 1.06675e-08, -5.90785e-09, -6.27815e-09]], "sigma_obs": [[0.147338]], "beta": [[-0.0830966, 0.46728, -1.87923, 0.722727, 1.29478, -0.306806, -1.98116, 0.198757, 0.775601, 2.70021, 0.838104, -1.08572, 1.63744, 1.62966, 1.73502, -0.280012, -2.6372, 1.61623, -0.364942, 1.99743, -0.0204143, -0.0423908, 0.0367853, 0.0293353, -0.0458706, -0.0104696, 0.0458706, -0.0104697, -0.0367853, 0.0293353, 0.0204143, -0.0423908, 1.22302e-08, 0.0470502, -0.0204143, -0.0423908, 0.0367853, 0.0293353, -0.0458706, -0.0104696, 0.0458706, -0.0104696, -0.0367853, 0.0293354, 0.0204143, -0.0423908, 2.40874e-08, 0.0470502, -0.0204143, -0.0423908, 0.0367853, 0.0293353, -0.0458705, -0.0104698, 0.0458706, -0.0104696, -0.0367853, 0.0293354, 0.0204143, -0.0423908, 3.00768e-08, 0.0470502, -0.0204143, -0.0423908, 0.0367853, 0.0293353, -0.0458706, -0.0104696, 0.0458705, -0.0104697, -0.0367853, 0.0293353, 0.0204143, -0.0423908, 4.86799e-08, 0.0470502, -0.0204143, -0.0423908, 0.0367853, 0.0293354, -0.0458706, -0.0104697, 0.0458706, -0.0104697, -0.0367853, 0.0293354, 0.0204145, -0.0423907, 5.49159e-08, 0.0470502, -0.0204142, -0.0423908, 0.0367853, 0.0293354, -0.0458706, -0.0104694, 0.0458706, -0.0104697, -0.0367853, 0.0293354, 0.0204145, -0.0423907, 5.98655e-08, 0.0470502, -0.0204141, -0.0423909, 0.0367853, 0.0293354, -0.0458706, -0.0104694, 0.0458706, -0.0104696, -0.0367854, 0.0293353, 0.0204142, -0.0423908, -5.30702e-08, 0.0470502, -0.0204145, -0.0423907, 0.0367853, 0.0293354, -0.0458706, -0.0104696, -0.153392, -4.09822e-12]], "trend": [[0.0113888, 0.0665219, 0.0730081, 0.0762512, 0.0827375, 0.0859806, 0.115169, 0.134627, 0.150843, 0.154086, 0.231921, 0.235164, 0.238407, 0.24165, 0.244894, 0.248137, 0.25138, 0.254623, 0.390834, 0.527045, 0.569206, 0.617853]]}, "__prophet_version": "1.1.5"}