{"growth": "linear", "n_changepoints": 25, "specified_changepoints": false, "changepoint_range": 0.8, "yearly_seasonality": "auto", "weekly_seasonality": 52, "daily_seasonality": "auto", "seasonality_mode": "additive", "seasonality_prior_scale": 10.0, "changepoint_prior_scale": 0.05, "holidays_prior_scale": 10.0, "mcmc_samples": 0, "interval_width": 0.8, "uncertainty_samples": 1000, "y_scale": 4.0, "y_min": 0.0, "scaling": "absmax", "logistic_floor": false, "country_holidays": null, "component_modes": {"additive": ["yearly", "weekly", "campaign", "discount_for_event", "additive_terms", "extra_regressors_additive", "holidays"], "multiplicative": ["multiplicative_terms", "extra_regressors_multiplicative"]}, "holidays_mode": "additive", "changepoints": "{\"name\":\"ds\",\"index\":[1,2,3,4,5,6,7,8,9,10,11,12,13,14,15,16,17,18,19,20,21,22,23,24,25],\"data\":[\"2018-09-03T00:00:00.000\",\"2018-10-08T00:00:00.000\",\"2018-10-29T00:00:00.000\",\"2019-02-25T00:00:00.000\",\"2019-08-12T00:00:00.000\",\"2019-08-19T00:00:00.000\",\"2019-09-02T00:00:00.000\",\"2019-09-16T00:00:00.000\",\"2020-03-02T00:00:00.000\",\"2020-09-07T00:00:00.000\",\"2021-02-01T00:00:00.000\",\"2021-08-30T00:00:00.000\",\"2021-09-06T00:00:00.000\",\"2021-09-13T00:00:00.000\",\"2021-11-29T00:00:00.000\",\"2022-03-07T00:00:00.000\",\"2022-08-22T00:00:00.000\",\"2022-08-29T00:00:00.000\",\"2022-09-05T00:00:00.000\",\"2022-09-12T00:00:00.000\",\"2022-09-19T00:00:00.000\",\"2022-10-03T00:00:00.000\",\"2023-01-16T00:00:00.000\",\"2023-02-20T00:00:00.000\",\"2023-05-01T00:00:00.000\"]}", "history_dates": "{\"name\":\"ds\",\"index\":[0,1,2,3,4,5,6,7,8,9,10,11,12,13,14,15,16,17,18,19,20,21,22,23,24,25,26,27,28,29,30,31,32],\"data\":[\"2018-08-27T00:00:00.000\",\"2018-09-03T00:00:00.000\",\"2018-10-08T00:00:00.000\",\"2018-10-29T00:00:00.000\",\"2019-02-25T00:00:00.000\",\"2019-08-12T00:00:00.000\",\"2019-08-19T00:00:00.000\",\"2019-09-02T00:00:00.000\",\"2019-09-16T00:00:00.000\",\"2020-03-02T00:00:00.000\",\"2020-09-07T00:00:00.000\",\"2021-02-01T00:00:00.000\",\"2021-08-30T00:00:00.000\",\"2021-09-06T00:00:00.000\",\"2021-09-13T00:00:00.000\",\"2021-11-29T00:00:00.000\",\"2022-03-07T00:00:00.000\",\"2022-08-22T00:00:00.000\",\"2022-08-29T00:00:00.000\",\"2022-09-05T00:00:00.000\",\"2022-09-12T00:00:00.000\",\"2022-09-19T00:00:00.000\",\"2022-10-03T00:00:00.000\",\"2023-01-16T00:00:00.000\",\"2023-02-20T00:00:00.000\",\"2023-05-01T00:00:00.000\",\"2023-05-08T00:00:00.000\",\"2023-08-14T00:00:00.000\",\"2023-08-21T00:00:00.000\",\"2023-08-28T00:00:00.000\",\"2023-09-04T00:00:00.000\",\"2023-09-11T00:00:00.000\",\"2023-12-04T00:00:00.000\"]}", "train_holiday_names": null, "start": 1535328000.0, "t_scale": 166320000.0, "holidays": null, "history": "{\"schema\":{\"fields\":[{\"name\":\"ds\",\"type\":\"datetime\"},{\"name\":\"y\",\"type\":\"integer\"},{\"name\":\"campaign\",\"type\":\"number\"},{\"name\":\"discount_for_event\",\"type\":\"number\"},{\"name\":\"floor\",\"type\":\"number\"},{\"name\":\"t\",\"type\":\"number\"},{\"name\":\"y_scaled\",\"type\":\"number\"}],\"pandas_version\":\"1.4.0\"},\"data\":[{\"ds\":\"2018-08-27T00:00:00.000\",\"y\":3,\"campaign\":0.0,\"discount_for_event\":0.0,\"floor\":0.0,\"t\":0.0,\"y_scaled\":0.75},{\"ds\":\"2018-09-03T00:00:00.000\",\"y\":4,\"campaign\":0.0,\"discount_for_event\":0.0,\"floor\":0.0,\"t\":0.0036363636,\"y_scaled\":1.0},{\"ds\":\"2018-10-08T00:00:00.000\",\"y\":1,\"campaign\":1.0,\"discount_for_event\":0.0,\"floor\":0.0,\"t\":0.0218181818,\"y_scaled\":0.25},{\"ds\":\"2018-10-29T00:00:00.000\",\"y\":1,\"campaign\":0.0,\"discount_for_event\":0.0,\"floor\":0.0,\"t\":0.0327272727,\"y_scaled\":0.25},{\"ds\":\"2019-02-25T00:00:00.000\",\"y\":1,\"campaign\":1.0,\"discount_for_event\":0.0,\"floor\":0.0,\"t\":0.0945454545,\"y_scaled\":0.25},{\"ds\":\"2019-08-12T00:00:00.000\",\"y\":1,\"campaign\":0.0,\"discount_for_event\":0.0,\"floor\":0.0,\"t\":0.1818181818,\"y_scaled\":0.25},{\"ds\":\"2019-08-19T00:00:00.000\",\"y\":1,\"campaign\":1.0,\"discount_for_event\":0.0,\"floor\":0.0,\"t\":0.1854545455,\"y_scaled\":0.25},{\"ds\":\"2019-09-02T00:00:00.000\",\"y\":4,\"campaign\":1.0,\"discount_for_event\":0.0,\"floor\":0.0,\"t\":0.1927272727,\"y_scaled\":1.0},{\"ds\":\"2019-09-16T00:00:00.000\",\"y\":1,\"campaign\":1.0,\"discount_for_event\":0.0,\"floor\":0.0,\"t\":0.2,\"y_scaled\":0.25},{\"ds\":\"2020-03-02T00:00:00.000\",\"y\":1,\"campaign\":1.0,\"discount_for_event\":0.0,\"floor\":0.0,\"t\":0.2872727273,\"y_scaled\":0.25},{\"ds\":\"2020-09-07T00:00:00.000\",\"y\":1,\"campaign\":1.0,\"discount_for_event\":0.0,\"floor\":0.0,\"t\":0.3854545455,\"y_scaled\":0.25},{\"ds\":\"2021-02-01T00:00:00.000\",\"y\":1,\"campaign\":1.0,\"discount_for_event\":0.0,\"floor\":0.0,\"t\":0.4618181818,\"y_scaled\":0.25},{\"ds\":\"2021-08-30T00:00:00.000\",\"y\":3,\"campaign\":0.0,\"discount_for_event\":0.0,\"floor\":0.0,\"t\":0.5709090909,\"y_scaled\":0.75},{\"ds\":\"2021-09-06T00:00:00.000\",\"y\":4,\"campaign\":0.0,\"discount_for_event\":0.0,\"floor\":0.0,\"t\":0.5745454545,\"y_scaled\":1.0},{\"ds\":\"2021-09-13T00:00:00.000\",\"y\":2,\"campaign\":0.0,\"discount_for_event\":0.0,\"floor\":0.0,\"t\":0.5781818182,\"y_scaled\":0.5},{\"ds\":\"2021-11-29T00:00:00.000\",\"y\":1,\"campaign\":1.0,\"discount_for_event\":0.0,\"floor\":0.0,\"t\":0.6181818182,\"y_scaled\":0.25},{\"ds\":\"2022-03-07T00:00:00.000\",\"y\":1,\"campaign\":1.0,\"discount_for_event\":0.0,\"floor\":0.0,\"t\":0.6690909091,\"y_scaled\":0.25},{\"ds\":\"2022-08-22T00:00:00.000\",\"y\":3,\"campaign\":1.0,\"discount_for_event\":0.0,\"floor\":0.0,\"t\":0.7563636364,\"y_scaled\":0.75},{\"ds\":\"2022-08-29T00:00:00.000\",\"y\":2,\"campaign\":0.0,\"discount_for_event\":0.0,\"floor\":0.0,\"t\":0.76,\"y_scaled\":0.5},{\"ds\":\"2022-09-05T00:00:00.000\",\"y\":3,\"campaign\":0.0,\"discount_for_event\":0.0,\"floor\":0.0,\"t\":0.7636363636,\"y_scaled\":0.75},{\"ds\":\"2022-09-12T00:00:00.000\",\"y\":2,\"campaign\":0.0,\"discount_for_event\":0.0,\"floor\":0.0,\"t\":0.7672727273,\"y_scaled\":0.5},{\"ds\":\"2022-09-19T00:00:00.000\",\"y\":1,\"campaign\":1.0,\"discount_for_event\":0.0,\"floor\":0.0,\"t\":0.7709090909,\"y_scaled\":0.25},{\"ds\":\"2022-10-03T00:00:00.000\",\"y\":1,\"campaign\":1.0,\"discount_for_event\":0.0,\"floor\":0.0,\"t\":0.7781818182,\"y_scaled\":0.25},{\"ds\":\"2023-01-16T00:00:00.000\",\"y\":1,\"campaign\":1.0,\"discount_for_event\":0.0,\"floor\":0.0,\"t\":0.8327272727,\"y_scaled\":0.25},{\"ds\":\"2023-02-20T00:00:00.000\",\"y\":1,\"campaign\":1.0,\"discount_for_event\":0.0,\"floor\":0.0,\"t\":0.8509090909,\"y_scaled\":0.25},{\"ds\":\"2023-05-01T00:00:00.000\",\"y\":1,\"campaign\":1.0,\"discount_for_event\":0.0,\"floor\":0.0,\"t\":0.8872727273,\"y_scaled\":0.25},{\"ds\":\"2023-05-08T00:00:00.000\",\"y\":1,\"campaign\":1.0,\"discount_for_event\":0.0,\"floor\":0.0,\"t\":0.8909090909,\"y_scaled\":0.25},{\"ds\":\"2023-08-14T00:00:00.000\",\"y\":1,\"campaign\":0.0,\"discount_for_event\":0.0,\"floor\":0.0,\"t\":0.9418181818,\"y_scaled\":0.25},{\"ds\":\"2023-08-21T00:00:00.000\",\"y\":1,\"campaign\":0.0,\"discount_for_event\":0.0,\"floor\":0.0,\"t\":0.9454545455,\"y_scaled\":0.25},{\"ds\":\"2023-08-28T00:00:00.000\",\"y\":2,\"campaign\":0.0,\"discount_for_event\":0.0,\"floor\":0.0,\"t\":0.9490909091,\"y_scaled\":0.5},{\"ds\":\"2023-09-04T00:00:00.000\",\"y\":1,\"campaign\":1.0,\"discount_for_event\":0.0,\"floor\":0.0,\"t\":0.9527272727,\"y_scaled\":0.25},{\"ds\":\"2023-09-11T00:00:00.000\",\"y\":1,\"campaign\":1.0,\"discount_for_event\":0.0,\"floor\":0.0,\"t\":0.9563636364,\"y_scaled\":0.25},{\"ds\":\"2023-12-04T00:00:00.000\",\"y\":1,\"campaign\":1.0,\"discount_for_event\":0.0,\"floor\":0.0,\"t\":1.0,\"y_scaled\":0.25}]}", "train_component_cols": "{\"schema\":{\"fields\":[{\"name\":\"additive_terms\",\"type\":\"integer\"},{\"name\":\"campaign\",\"type\":\"integer\"},{\"name\":\"discount_for_event\",\"type\":\"integer\"},{\"name\":\"extra_regressors_additive\",\"type\":\"integer\"},{\"name\":\"weekly\",\"type\":\"integer\"},{\"name\":\"yearly\",\"type\":\"integer\"},{\"name\":\"multiplicative_terms\",\"type\":\"integer\"}],\"pandas_version\":\"1.4.0\"},\"data\":[{\"additive_terms\":1,\"campaign\":0,\"discount_for_event\":0,\"extra_regressors_additive\":0,\"weekly\":0,\"yearly\":1,\"multiplicative_terms\":0},{\"additive_terms\":1,\"campaign\":0,\"discount_for_event\":0,\"extra_regressors_additive\":0,\"weekly\":0,\"yearly\":1,\"multiplicative_terms\":0},{\"additive_terms\":1,\"campaign\":0,\"discount_for_event\":0,\"extra_regressors_additive\":0,\"weekly\":0,\"yearly\":1,\"multiplicative_terms\":0},{\"additive_terms\":1,\"campaign\":0,\"discount_for_event\":0,\"extra_regressors_additive\":0,\"weekly\":0,\"yearly\":1,\"multiplicative_terms\":0},{\"additive_terms\":1,\"campaign\":0,\"discount_for_event\":0,\"extra_regressors_additive\":0,\"weekly\":0,\"yearly\":1,\"multiplicative_terms\":0},{\"additive_terms\":1,\"campaign\":0,\"discount_for_event\":0,\"extra_regressors_additive\":0,\"weekly\":0,\"yearly\":1,\"multiplicative_terms\":0},{\"additive_terms\":1,\"campaign\":0,\"discount_for_event\":0,\"extra_regressors_additive\":0,\"weekly\":0,\"yearly\":1,\"multiplicative_terms\":0},{\"additive_terms\":1,\"campaign\":0,\"discount_for_event\":0,\"extra_regressors_additive\":0,\"weekly\":0,\"yearly\":1,\"multiplicative_terms\":0},{\"additive_terms\":1,\"campaign\":0,\"discount_for_event\":0,\"extra_regressors_additive\":0,\"weekly\":0,\"yearly\":1,\"multiplicative_terms\":0},{\"additive_terms\":1,\"campaign\":0,\"discount_for_event\":0,\"extra_regressors_additive\":0,\"weekly\":0,\"yearly\":1,\"multiplicative_terms\":0},{\"additive_terms\":1,\"campaign\":0,\"discount_for_event\":0,\"extra_regressors_additive\":0,\"weekly\":0,\"yearly\":1,\"multiplicative_terms\":0},{\"additive_terms\":1,\"campaign\":0,\"discount_for_event\":0,\"extra_regressors_additive\":0,\"weekly\":0,\"yearly\":1,\"multiplicative_terms\":0},{\"additive_terms\":1,\"campaign\":0,\"discount_for_event\":0,\"extra_regressors_additive\":0,\"weekly\":0,\"yearly\":1,\"multiplicative_terms\":0},{\"additive_terms\":1,\"campaign\":0,\"discount_for_event\":0,\"extra_regressors_additive\":0,\"weekly\":0,\"yearly\":1,\"multiplicative_terms\":0},{\"additive_terms\":1,\"campaign\":0,\"discount_for_event\":0,\"extra_regressors_additive\":0,\"weekly\":0,\"yearly\":1,\"multiplicative_terms\":0},{\"additive_terms\":1,\"campaign\":0,\"discount_for_event\":0,\"extra_regressors_additive\":0,\"weekly\":0,\"yearly\":1,\"multiplicative_terms\":0},{\"additive_terms\":1,\"campaign\":0,\"discount_for_event\":0,\"extra_regressors_additive\":0,\"weekly\":0,\"yearly\":1,\"multiplicative_terms\":0},{\"additive_terms\":1,\"campaign\":0,\"discount_for_event\":0,\"extra_regressors_additive\":0,\"weekly\":0,\"yearly\":1,\"multiplicative_terms\":0},{\"additive_terms\":1,\"campaign\":0,\"discount_for_event\":0,\"extra_regressors_additive\":0,\"weekly\":0,\"yearly\":1,\"multiplicative_terms\":0},{\"additive_terms\":1,\"campaign\":0,\"discount_for_event\":0,\"extra_regressors_additive\":0,\"weekly\":0,\"yearly\":1,\"multiplicative_terms\":0},{\"additive_terms\":1,\"campaign\":0,\"discount_for_event\":0,\"extra_regressors_additive\":0,\"weekly\":1,\"yearly\":0,\"multiplicative_terms\":0},{\"additive_terms\":1,\"campaign\":0,\"discount_for_event\":0,\"extra_regressors_additive\":0,\"weekly\":1,\"yearly\":0,\"multiplicative_terms\":0},{\"additive_terms\":1,\"campaign\":0,\"discount_for_event\":0,\"extra_regressors_additive\":0,\"weekly\":1,\"yearly\":0,\"multiplicative_terms\":0},{\"additive_terms\":1,\"campaign\":0,\"discount_for_event\":0,\"extra_regressors_additive\":0,\"weekly\":1,\"yearly\":0,\"multiplicative_terms\":0},{\"additive_terms\":1,\"campaign\":0,\"discount_for_event\":0,\"extra_regressors_additive\":0,\"weekly\":1,\"yearly\":0,\"multiplicative_terms\":0},{\"additive_terms\":1,\"campaign\":0,\"discount_for_event\":0,\"extra_regressors_additive\":0,\"weekly\":1,\"yearly\":0,\"multiplicative_terms\":0},{\"additive_terms\":1,\"campaign\":0,\"discount_for_event\":0,\"extra_regressors_additive\":0,\"weekly\":1,\"yearly\":0,\"multiplicative_terms\":0},{\"additive_terms\":1,\"campaign\":0,\"discount_for_event\":0,\"extra_regressors_additive\":0,\"weekly\":1,\"yearly\":0,\"multiplicative_terms\":0},{\"additive_terms\":1,\"campaign\":0,\"discount_for_event\":0,\"extra_regressors_additive\":0,\"weekly\":1,\"yearly\":0,\"multiplicative_terms\":0},{\"additive_terms\":1,\"campaign\":0,\"discount_for_event\":0,\"extra_regressors_additive\":0,\"weekly\":1,\"yearly\":0,\"multiplicative_terms\":0},{\"additive_terms\":1,\"campaign\":0,\"discount_for_event\":0,\"extra_regressors_additive\":0,\"weekly\":1,\"yearly\":0,\"multiplicative_terms\":0},{\"additive_terms\":1,\"campaign\":0,\"discount_for_event\":0,\"extra_regressors_additive\":0,\"weekly\":1,\"yearly\":0,\"multiplicative_terms\":0},{\"additive_terms\":1,\"campaign\":0,\"discount_for_event\":0,\"extra_regressors_additive\":0,\"weekly\":1,\"yearly\":0,\"multiplicative_terms\":0},{\"additive_terms\":1,\"campaign\":0,\"discount_for_event\":0,\"extra_regressors_additive\":0,\"weekly\":1,\"yearly\":0,\"multiplicative_terms\":0},{\"additive_terms\":1,\"campaign\":0,\"discount_for_event\":0,\"extra_regressors_additive\":0,\"weekly\":1,\"yearly\":0,\"multiplicative_terms\":0},{\"additive_terms\":1,\"campaign\":0,\"discount_for_event\":0,\"extra_regressors_additive\":0,\"weekly\":1,\"yearly\":0,\"multiplicative_terms\":0},{\"additive_terms\":1,\"campaign\":0,\"discount_for_event\":0,\"extra_regressors_additive\":0,\"weekly\":1,\"yearly\":0,\"multiplicative_terms\":0},{\"additive_terms\":1,\"campaign\":0,\"discount_for_event\":0,\"extra_regressors_additive\":0,\"weekly\":1,\"yearly\":0,\"multiplicative_terms\":0},{\"additive_terms\":1,\"campaign\":0,\"discount_for_event\":0,\"extra_regressors_additive\":0,\"weekly\":1,\"yearly\":0,\"multiplicative_terms\":0},{\"additive_terms\":1,\"campaign\":0,\"discount_for_event\":0,\"extra_regressors_additive\":0,\"weekly\":1,\"yearly\":0,\"multiplicative_terms\":0},{\"additive_terms\":1,\"campaign\":0,\"discount_for_event\":0,\"extra_regressors_additive\":0,\"weekly\":1,\"yearly\":0,\"multiplicative_terms\":0},{\"additive_terms\":1,\"campaign\":0,\"discount_for_event\":0,\"extra_regressors_additive\":0,\"weekly\":1,\"yearly\":0,\"multiplicative_terms\":0},{\"additive_terms\":1,\"campaign\":0,\"discount_for_event\":0,\"extra_regressors_additive\":0,\"weekly\":1,\"yearly\":0,\"multiplicative_terms\":0},{\"additive_terms\":1,\"campaign\":0,\"discount_for_event\":0,\"extra_regressors_additive\":0,\"weekly\":1,\"yearly\":0,\"multiplicative_terms\":0},{\"additive_terms\":1,\"campaign\":0,\"discount_for_event\":0,\"extra_regressors_additive\":0,\"weekly\":1,\"yearly\":0,\"multiplicative_terms\":0},{\"additive_terms\":1,\"campaign\":0,\"discount_for_event\":0,\"extra_regressors_additive\":0,\"weekly\":1,\"yearly\":0,\"multiplicative_terms\":0},{\"additive_terms\":1,\"campaign\":0,\"discount_for_event\":0,\"extra_regressors_additive\":0,\"weekly\":1,\"yearly\":0,\"multiplicative_terms\":0},{\"additive_terms\":1,\"campaign\":0,\"discount_for_event\":0,\"extra_regressors_additive\":0,\"weekly\":1,\"yearly\":0,\"multiplicative_terms\":0},{\"additive_terms\":1,\"campaign\":0,\"discount_for_event\":0,\"extra_regressors_additive\":0,\"weekly\":1,\"yearly\":0,\"multiplicative_terms\":0},{\"additive_terms\":1,\"campaign\":0,\"discount_for_event\":0,\"extra_regressors_additive\":0,\"weekly\":1,\"yearly\":0,\"multiplicative_terms\":0},{\"additive_terms\":1,\"campaign\":0,\"discount_for_event\":0,\"extra_regressors_additive\":0,\"weekly\":1,\"yearly\":0,\"multiplicative_terms\":0},{\"additive_terms\":1,\"campaign\":0,\"discount_for_event\":0,\"extra_regressors_additive\":0,\"weekly\":1,\"yearly\":0,\"multiplicative_terms\":0},{\"additive_terms\":1,\"campaign\":0,\"discount_for_event\":0,\"extra_regressors_additive\":0,\"weekly\":1,\"yearly\":0,\"multiplicative_terms\":0},{\"additive_terms\":1,\"campaign\":0,\"discount_for_event\":0,\"extra_regressors_additive\":0,\"weekly\":1,\"yearly\":0,\"multiplicative_terms\":0},{\"additive_terms\":1,\"campaign\":0,\"discount_for_event\":0,\"extra_regressors_additive\":0,\"weekly\":1,\"yearly\":0,\"multiplicative_terms\":0},{\"additive_terms\":1,\"campaign\":0,\"discount_for_event\":0,\"extra_regressors_additive\":0,\"weekly\":1,\"yearly\":0,\"multiplicative_terms\":0},{\"additive_terms\":1,\"campaign\":0,\"discount_for_event\":0,\"extra_regressors_additive\":0,\"weekly\":1,\"yearly\":0,\"multiplicative_terms\":0},{\"additive_terms\":1,\"campaign\":0,\"discount_for_event\":0,\"extra_regressors_additive\":0,\"weekly\":1,\"yearly\":0,\"multiplicative_terms\":0},{\"additive_terms\":1,\"campaign\":0,\"discount_for_event\":0,\"extra_regressors_additive\":0,\"weekly\":1,\"yearly\":0,\"multiplicative_terms\":0},{\"additive_terms\":1,\"campaign\":0,\"discount_for_event\":0,\"extra_regressors_additive\":0,\"weekly\":1,\"yearly\":0,\"multiplicative_terms\":0},{\"additive_terms\":1,\"campaign\":0,\"discount_for_event\":0,\"extra_regressors_additive\":0,\"weekly\":1,\"yearly\":0,\"multiplicative_terms\":0},{\"additive_terms\":1,\"campaign\":0,\"discount_for_event\":0,\"extra_regressors_additive\":0,\"weekly\":1,\"yearly\":0,\"multiplicative_terms\":0},{\"additive_terms\":1,\"campaign\":0,\"discount_for_event\":0,\"extra_regressors_additive\":0,\"weekly\":1,\"yearly\":0,\"multiplicative_terms\":0},{\"additive_terms\":1,\"campaign\":0,\"discount_for_event\":0,\"extra_regressors_additive\":0,\"weekly\":1,\"yearly\":0,\"multiplicative_terms\":0},{\"additive_terms\":1,\"campaign\":0,\"discount_for_event\":0,\"extra_regressors_additive\":0,\"weekly\":1,\"yearly\":0,\"multiplicative_terms\":0},{\"additive_terms\":1,\"campaign\":0,\"discount_for_event\":0,\"extra_regressors_additive\":0,\"weekly\":1,\"yearly\":0,\"multiplicative_terms\":0},{\"additive_terms\":1,\"campaign\":0,\"discount_for_event\":0,\"extra_regressors_additive\":0,\"weekly\":1,\"yearly\":0,\"multiplicative_terms\":0},{\"additive_terms\":1,\"campaign\":0,\"discount_for_event\":0,\"extra_regressors_additive\":0,\"weekly\":1,\"yearly\":0,\"multiplicative_terms\":0},{\"additive_terms\":1,\"campaign\":0,\"discount_for_event\":0,\"extra_regressors_additive\":0,\"weekly\":1,\"yearly\":0,\"multiplicative_terms\":0},{\"additive_terms\":1,\"campaign\":0,\"discount_for_event\":0,\"extra_regressors_additive\":0,\"weekly\":1,\"yearly\":0,\"multiplicative_terms\":0},{\"additive_terms\":1,\"campaign\":0,\"discount_for_event\":0,\"extra_regressors_additive\":0,\"weekly\":1,\"yearly\":0,\"multiplicative_terms\":0},{\"additive_terms\":1,\"campaign\":0,\"discount_for_event\":0,\"extra_regressors_additive\":0,\"weekly\":1,\"yearly\":0,\"multiplicative_terms\":0},{\"additive_terms\":1,\"campaign\":0,\"discount_for_event\":0,\"extra_regressors_additive\":0,\"weekly\":1,\"yearly\":0,\"multiplicative_terms\":0},{\"additive_terms\":1,\"campaign\":0,\"discount_for_event\":0,\"extra_regressors_additive\":0,\"weekly\":1,\"yearly\":0,\"multiplicative_terms\":0},{\"additive_terms\":1,\"campaign\":0,\"discount_for_event\":0,\"extra_regressors_additive\":0,\"weekly\":1,\"yearly\":0,\"multiplicative_terms\":0},{\"additive_terms\":1,\"campaign\":0,\"discount_for_event\":0,\"extra_regressors_additive\":0,\"weekly\":1,\"yearly\":0,\"multiplicative_terms\":0},{\"additive_terms\":1,\"campaign\":0,\"discount_for_event\":0,\"extra_regressors_additive\":0,\"weekly\":1,\"yearly\":0,\"multiplicative_terms\":0},{\"additive_terms\":1,\"campaign\":0,\"discount_for_event\":0,\"extra_regressors_additive\":0,\"weekly\":1,\"yearly\":0,\"multiplicative_terms\":0},{\"additive_terms\":1,\"campaign\":0,\"discount_for_event\":0,\"extra_regressors_additive\":0,\"weekly\":1,\"yearly\":0,\"multiplicative_terms\":0},{\"additive_terms\":1,\"campaign\":0,\"discount_for_event\":0,\"extra_regressors_additive\":0,\"weekly\":1,\"yearly\":0,\"multiplicative_terms\":0},{\"additive_terms\":1,\"campaign\":0,\"discount_for_event\":0,\"extra_regressors_additive\":0,\"weekly\":1,\"yearly\":0,\"multiplicative_terms\":0},{\"additive_terms\":1,\"campaign\":0,\"discount_for_event\":0,\"extra_regressors_additive\":0,\"weekly\":1,\"yearly\":0,\"multiplicative_terms\":0},{\"additive_terms\":1,\"campaign\":0,\"discount_for_event\":0,\"extra_regressors_additive\":0,\"weekly\":1,\"yearly\":0,\"multiplicative_terms\":0},{\"additive_terms\":1,\"campaign\":0,\"discount_for_event\":0,\"extra_regressors_additive\":0,\"weekly\":1,\"yearly\":0,\"multiplicative_terms\":0},{\"additive_terms\":1,\"campaign\":0,\"discount_for_event\":0,\"extra_regressors_additive\":0,\"weekly\":1,\"yearly\":0,\"multiplicative_terms\":0},{\"additive_terms\":1,\"campaign\":0,\"discount_for_event\":0,\"extra_regressors_additive\":0,\"weekly\":1,\"yearly\":0,\"multiplicative_terms\":0},{\"additive_terms\":1,\"campaign\":0,\"discount_for_event\":0,\"extra_regressors_additive\":0,\"weekly\":1,\"yearly\":0,\"multiplicative_terms\":0},{\"additive_terms\":1,\"campaign\":0,\"discount_for_event\":0,\"extra_regressors_additive\":0,\"weekly\":1,\"yearly\":0,\"multiplicative_terms\":0},{\"additive_terms\":1,\"campaign\":0,\"discount_for_event\":0,\"extra_regressors_additive\":0,\"weekly\":1,\"yearly\":0,\"multiplicative_terms\":0},{\"additive_terms\":1,\"campaign\":0,\"discount_for_event\":0,\"extra_regressors_additive\":0,\"weekly\":1,\"yearly\":0,\"multiplicative_terms\":0},{\"additive_terms\":1,\"campaign\":0,\"discount_for_event\":0,\"extra_regressors_additive\":0,\"weekly\":1,\"yearly\":0,\"multiplicative_terms\":0},{\"additive_terms\":1,\"campaign\":0,\"discount_for_event\":0,\"extra_regressors_additive\":0,\"weekly\":1,\"yearly\":0,\"multiplicative_terms\":0},{\"additive_terms\":1,\"campaign\":0,\"discount_for_event\":0,\"extra_regressors_additive\":0,\"weekly\":1,\"yearly\":0,\"multiplicative_terms\":0},{\"additive_terms\":1,\"campaign\":0,\"discount_for_event\":0,\"extra_regressors_additive\":0,\"weekly\":1,\"yearly\":0,\"multiplicative_terms\":0},{\"additive_terms\":1,\"campaign\":0,\"discount_for_event\":0,\"extra_regressors_additive\":0,\"weekly\":1,\"yearly\":0,\"multiplicative_terms\":0},{\"additive_terms\":1,\"campaign\":0,\"discount_for_event\":0,\"extra_regressors_additive\":0,\"weekly\":1,\"yearly\":0,\"multiplicative_terms\":0},{\"additive_terms\":1,\"campaign\":0,\"discount_for_event\":0,\"extra_regressors_additive\":0,\"weekly\":1,\"yearly\":0,\"multiplicative_terms\":0},{\"additive_terms\":1,\"campaign\":0,\"discount_for_event\":0,\"extra_regressors_additive\":0,\"weekly\":1,\"yearly\":0,\"multiplicative_terms\":0},{\"additive_terms\":1,\"campaign\":0,\"discount_for_event\":0,\"extra_regressors_additive\":0,\"weekly\":1,\"yearly\":0,\"multiplicative_terms\":0},{\"additive_terms\":1,\"campaign\":0,\"discount_for_event\":0,\"extra_regressors_additive\":0,\"weekly\":1,\"yearly\":0,\"multiplicative_terms\":0},{\"additive_terms\":1,\"campaign\":0,\"discount_for_event\":0,\"extra_regressors_additive\":0,\"weekly\":1,\"yearly\":0,\"multiplicative_terms\":0},{\"additive_terms\":1,\"campaign\":0,\"discount_for_event\":0,\"extra_regressors_additive\":0,\"weekly\":1,\"yearly\":0,\"multiplicative_terms\":0},{\"additive_terms\":1,\"campaign\":0,\"discount_for_event\":0,\"extra_regressors_additive\":0,\"weekly\":1,\"yearly\":0,\"multiplicative_terms\":0},{\"additive_terms\":1,\"campaign\":0,\"discount_for_event\":0,\"extra_regressors_additive\":0,\"weekly\":1,\"yearly\":0,\"multiplicative_terms\":0},{\"additive_terms\":1,\"campaign\":0,\"discount_for_event\":0,\"extra_regressors_additive\":0,\"weekly\":1,\"yearly\":0,\"multiplicative_terms\":0},{\"additive_terms\":1,\"campaign\":0,\"discount_for_event\":0,\"extra_regressors_additive\":0,\"weekly\":1,\"yearly\":0,\"multiplicative_terms\":0},{\"additive_terms\":1,\"campaign\":0,\"discount_for_event\":0,\"extra_regressors_additive\":0,\"weekly\":1,\"yearly\":0,\"multiplicative_terms\":0},{\"additive_terms\":1,\"campaign\":0,\"discount_for_event\":0,\"extra_regressors_additive\":0,\"weekly\":1,\"yearly\":0,\"multiplicative_terms\":0},{\"additive_terms\":1,\"campaign\":0,\"discount_for_event\":0,\"extra_regressors_additive\":0,\"weekly\":1,\"yearly\":0,\"multiplicative_terms\":0},{\"additive_terms\":1,\"campaign\":0,\"discount_for_event\":0,\"extra_regressors_additive\":0,\"weekly\":1,\"yearly\":0,\"multiplicative_terms\":0},{\"additive_terms\":1,\"campaign\":0,\"discount_for_event\":0,\"extra_regressors_additive\":0,\"weekly\":1,\"yearly\":0,\"multiplicative_terms\":0},{\"additive_terms\":1,\"campaign\":0,\"discount_for_event\":0,\"extra_regressors_additive\":0,\"weekly\":1,\"yearly\":0,\"multiplicative_terms\":0},{\"additive_terms\":1,\"campaign\":0,\"discount_for_event\":0,\"extra_regressors_additive\":0,\"weekly\":1,\"yearly\":0,\"multiplicative_terms\":0},{\"additive_terms\":1,\"campaign\":0,\"discount_for_event\":0,\"extra_regressors_additive\":0,\"weekly\":1,\"yearly\":0,\"multiplicative_terms\":0},{\"additive_terms\":1,\"campaign\":0,\"discount_for_event\":0,\"extra_regressors_additive\":0,\"weekly\":1,\"yearly\":0,\"multiplicative_terms\":0},{\"additive_terms\":1,\"campaign\":0,\"discount_for_event\":0,\"extra_regressors_additive\":0,\"weekly\":1,\"yearly\":0,\"multiplicative_terms\":0},{\"additive_terms\":1,\"campaign\":0,\"discount_for_event\":0,\"extra_regressors_additive\":0,\"weekly\":1,\"yearly\":0,\"multiplicative_terms\":0},{\"additive_terms\":1,\"campaign\":0,\"discount_for_event\":0,\"extra_regressors_additive\":0,\"weekly\":1,\"yearly\":0,\"multiplicative_terms\":0},{\"additive_terms\":1,\"campaign\":0,\"discount_for_event\":0,\"extra_regressors_additive\":0,\"weekly\":1,\"yearly\":0,\"multiplicative_terms\":0},{\"additive_terms\":1,\"campaign\":0,\"discount_for_event\":0,\"extra_regressors_additive\":0,\"weekly\":1,\"yearly\":0,\"multiplicative_terms\":0},{\"additive_terms\":1,\"campaign\":0,\"discount_for_event\":0,\"extra_regressors_additive\":0,\"weekly\":1,\"yearly\":0,\"multiplicative_terms\":0},{\"additive_terms\":1,\"campaign\":0,\"discount_for_event\":0,\"extra_regressors_additive\":0,\"weekly\":1,\"yearly\":0,\"multiplicative_terms\":0},{\"additive_terms\":1,\"campaign\":0,\"discount_for_event\":0,\"extra_regressors_additive\":0,\"weekly\":1,\"yearly\":0,\"multiplicative_terms\":0},{\"additive_terms\":1,\"campaign\":0,\"discount_for_event\":0,\"extra_regressors_additive\":0,\"weekly\":1,\"yearly\":0,\"multiplicative_terms\":0},{\"additive_terms\":1,\"campaign\":1,\"discount_for_event\":0,\"extra_regressors_additive\":1,\"weekly\":0,\"yearly\":0,\"multiplicative_terms\":0},{\"additive_terms\":1,\"campaign\":0,\"discount_for_event\":1,\"extra_regressors_additive\":1,\"weekly\":0,\"yearly\":0,\"multiplicative_terms\":0}]}", "changepoints_t": [0.0036363636363636364, 0.02181818181818182, 0.03272727272727273, 0.09454545454545454, 0.18181818181818182, 0.18545454545454546, 0.19272727272727272, 0.2, 0.2872727272727273, 0.38545454545454544, 0.4618181818181818, 0.5709090909090909, 0.5745454545454546, 0.5781818181818181, 0.6181818181818182, 0.6690909090909091, 0.7563636363636363, 0.76, 0.7636363636363637, 0.7672727272727272, 0.7709090909090909, 0.7781818181818182, 0.8327272727272728, 0.850909090909091, 0.8872727272727273], "seasonalities": [["yearly", "weekly"], {"yearly": {"period": 365.25, "fourier_order": 10, "prior_scale": 10.0, "mode": "additive", "condition_name": null}, "weekly": {"period": 7, "fourier_order": 52, "prior_scale": 10.0, "mode": "additive", "condition_name": null}}], "extra_regressors": [["campaign", "discount_for_event"], {"campaign": {"prior_scale": 10.0, "standardize": "auto", "mu": 0.0, "std": 1.0, "mode": "additive"}, "discount_for_event": {"prior_scale": 10.0, "standardize": "auto", "mu": 0.0, "std": 1.0, "mode": "additive"}}], "fit_kwargs": {}, "params": {"lp__": [[48.5515]], "k": [[-0.297084]], "m": [[0.00212027]], "delta": [[2.20839e-10, 1.60988e-10, 2.10757e-10, -1.42285e-10, 9.98491e-11, 2.97344e-11, -2.67431e-10, -2.39601e-10, 2.22317e-10, 2.13274e-10, 7.59409e-11, -4.5052e-10, -3.4629e-10, -3.63901e-10, 2.72003e-10, -2.35384e-10, -2.67622e-09, 1.83742e-12, -2.41676e-10, -3.45644e-10, 6.69409e-11, -6.76995e-11, 2.71333e-10, -1.60685e-10, 7.28045e-11]], "sigma_obs": [[0.138639]], "beta": [[-0.613621, 1.92906, -0.533013, 0.805301, 0.531378, 0.896993, -1.3897, -0.0324349, 0.385215, 0.576887, -1.00736, 0.882939, 0.837144, 0.506352, -1.36229, 0.226032, -0.110478, 0.683973, -0.382079, -0.0869245, -0.00331875, -0.00689148, 0.00598019, 0.00476906, -0.00745719, -0.00170206, 0.0074572, -0.00170202, -0.0059802, 0.00476906, 0.00331876, -0.00689148, 3.502e-09, 0.00764896, -0.0033187, -0.00689151, 0.00598023, 0.00476901, -0.00745719, -0.00170204, 0.00745718, -0.00170208, -0.00598021, 0.00476905, 0.00331876, -0.00689148, 7.00502e-09, 0.00764896, -0.00331873, -0.00689149, 0.00598011, 0.00476916, -0.00745721, -0.00170196, 0.00745716, -0.00170216, -0.0059801, 0.00476917, 0.00331874, -0.00689149, 1.08924e-07, 0.00764896, -0.0033188, -0.00689146, 0.00598011, 0.00476917, -0.00745719, -0.00170207, 0.00745719, -0.00170205, -0.0059802, 0.00476905, 0.00331894, -0.00689139, 1.40139e-08, 0.00764896, -0.00331869, -0.00689151, 0.00598016, 0.00476911, -0.00745718, -0.00170211, 0.00745725, -0.00170178, -0.00598019, 0.00476906, 0.00331859, -0.00689156, -9.99443e-08, 0.00764896, -0.00331895, -0.00689139, 0.00598021, 0.00476903, -0.00745726, -0.00170175, 0.00745722, -0.00170193, -0.00598017, 0.00476909, 0.00331918, -0.00689128, 2.17857e-07, 0.00764896, -0.00331896, -0.00689138, 0.00598026, 0.00476898, -0.00745722, -0.00170194, 0.00745725, -0.00170177, -0.00598011, 0.00476917, 0.00331879, -0.00689147, -8.99031e-09, 0.00764896, -0.00331875, -0.00689149, 0.00597994, 0.00476938, -0.00745719, -0.00170205, -0.173693, -8.00623e-14]], "trend": [[0.00212027, 0.00103996, -0.00436156, -0.00760247, -0.0259676, -0.051895, -0.0529753, -0.0551359, -0.0572965, -0.0832238, -0.112392, -0.135078, -0.167488, -0.168568, -0.169648, -0.181531, -0.196656, -0.222583, -0.223663, -0.224744, -0.225824, -0.226904, -0.229065, -0.245269, -0.250671, -0.261474, -0.262554, -0.277679, -0.278759, -0.279839, -0.28092, -0.282, -0.294963]]}, "__prophet_version": "1.1.5"}